Workbook
Name BSCheck: BS!$F$58
Name circularityswitch: Guide!$E$20
Name COY: Guide!$E$8
Name currency: Guide!$E$19
Name livescenario: Scenario!$D$12
Name scenariolist: Scenario!$D$13:$D$15
Name scenarioswitch: Scenario!$F$13

Sheet Cover Page

Sheet Guide
B2: =COY -> Fidson Healthcare Plc
C3: Model Guide
B6: General Information
C7: General information
D8: Company name | E8: Fidson Healthcare Plc
D9: Industry | E9: FMCG
D10: Business Location | E10: Nigeria
C13: Model information
D14: Model first historical year | E14: 44562
D15: Last historical year | E15: 45657
D16: Forecast Start Date | E16: =E15+1 -> 45658
D17: Forecast Years | E17: 5
D18: Forecast End Date | E18: =DATE(YEAR(E16)+E17-1,12,31) -> 47483
D19: Model Currency | E19: (₦'000)
D20: Circularity Toggle | E20: Yes
C22: Formatting guide
D23: Style | E23: Sample | F23: Meaning
D24: Title | E24: Text | F24: Shows the title of a sheet or model
D25: Heading 1 | E25: Text | F25: Shows the beginning of a section in the model
D26: Heading 2 | E26: Text | F26: Shows the subsection or calculation block in the model
D27: Table Header | E27: Table | F27: Headers for table in the model
D28: Input Cell style | E28: 1234.5 | F28: Cell contains input that users can alter
D29: Normal style | E29: 1234.56 | F29: Cells contain formulas users should not alter
D30: Linked cells | E30: 1234.5 | F30: Cells whose values are linked from another cell
D31: Percentage style | E31: 0.01 | F31: Values expressed in percentages
D32: Unit/Explanatory style | E32: units | F32: Provides context to a row of data

Sheet summary
B2: =COY -> Fidson Healthcare Plc
C3: Executive summary
D5: ="Balance sheet check: " &BSCheck -> Balance sheet check: OK
D6: {=livescenario} -> Live Scenario: Base case
D16: Income Statement Summary | E16: Trend | F16: 2023H | G16: 2024H | H16: 2025H | I16: 2026F | J16: 2027F | K16: 2028F | L16: 2029F
D17: ='P or L'!D13 -> Revenue from contracts with customers | F17: ='P or L'!L13 -> 53050354 | G17: ='P or L'!M13 -> 84189000 | H17: ='P or L'!N13 -> 119061254 | I17: ='P or L'!O13 -> 1.7092191e+08 | J17: ='P or L'!P13 -> 2.3416302e+08 | K17: ='P or L'!Q13 -> 3.0675355e+08 | L17: ='P or L'!R13 -> 3.8344194e+08
D18: ='P or L'!D14 -> Cost of Sales | F18: ='P or L'!L14 -> 29600790 | G18: ='P or L'!M14 -> 46089425 | H18: ='P or L'!N14 -> 66296769 | I18: ='P or L'!O14 -> 94705341 | J18: ='P or L'!P14 -> 1.2974632e+08 | K18: ='P or L'!Q14 -> 1.6996768e+08 | L18: ='P or L'!R14 -> 2.124596e+08
D19: ='P or L'!D15 -> Gross Profit | F19: ='P or L'!L15 -> 23449564 | G19: ='P or L'!M15 -> 38099575 | H19: ='P or L'!N15 -> 52764485 | I19: ='P or L'!O15 -> 76216570 | J19: ='P or L'!P15 -> 1.044167e+08 | K19: ='P or L'!Q15 -> 1.3678588e+08 | L19: ='P or L'!R15 -> 1.7098235e+08
D20: ='P or L'!D19 -> EBITDA | F20: ='P or L'!L19 -> 10752033 | G20: ='P or L'!M19 -> 20552241 | H20: ='P or L'!N19 -> 30332592 | I20: ='P or L'!O19 -> 39970707 | J20: ='P or L'!P19 -> 54759869 | K20: ='P or L'!Q19 -> 71735428 | L20: ='P or L'!R19 -> 89669285
D21: ='P or L'!D23 -> EBIT (Operating Profit) | F21: ='P or L'!L23 -> 9485296 | G21: ='P or L'!M23 -> 18884591 | H21: ='P or L'!N23 -> 28093748 | I21: ='P or L'!O23 -> 36846699 | J21: ='P or L'!P23 -> 51159698 | K21: ='P or L'!Q23 -> 67455385 | L21: ='P or L'!R23 -> 84415967
D22: ='P or L'!D28 -> Profit before taxation | F22: ='P or L'!L28 -> 5917409 | G22: ='P or L'!M28 -> 7700460 | H22: ='P or L'!N28 -> 14962608 | I22: ='P or L'!O28 -> 23790119 | J22: ='P or L'!P28 -> 35604987 | K22: ='P or L'!Q28 -> 50031143 | L22: ='P or L'!R28 -> 65810027
D23: ='P or L'!D29 -> Taxation | F23: ='P or L'!L29 -> 2309816 | G23: ='P or L'!M29 -> 3301497 | H23: ='P or L'!N29 -> 5079032 | I23: ='P or L'!O29 -> 9137648.3 | J23: ='P or L'!P29 -> 13675672 | K23: ='P or L'!Q29 -> 19216675 | L23: ='P or L'!R29 -> 25277254
D24: ='P or L'!D30 -> Profit for the year | F24: ='P or L'!L30 -> 3607593 | G24: ='P or L'!M30 -> 4398963 | H24: ='P or L'!N30 -> 9883576 | I24: ='P or L'!O30 -> 14652470 | J24: ='P or L'!P30 -> 21929316 | K24: ='P or L'!Q30 -> 30814468 | L24: ='P or L'!R30 -> 40532772
D27: Balance Sheet Summary | E27: Trend | F27: 2023H | G27: 2024H | H27: 2025H | I27: 2026F | J27: 2027F | K27: 2028F | L27: 2029F
D28: =BS!D23 -> Total Non-current Assets | F28: =BS!L23 -> 23706144 | G28: =BS!M23 -> 25658570 | H28: =BS!N23 -> 31424875 | I28: =BS!O23 -> 31737276 | J28: =BS!P23 -> 32097293 | K28: =BS!Q23 -> 32525297 | L28: =BS!R23 -> 33050629
D29: =BS!D30 -> Total Current Assets | F29: =BS!L30 -> 38284982 | G29: =BS!M30 -> 47834910 | H29: =BS!N30 -> 48862064 | I29: =BS!O30 -> 80952233 | J29: =BS!P30 -> 1.100711e+08 | K29: =BS!Q30 -> 1.4349484e+08 | L29: =BS!R30 -> 1.788054e+08
D30: =BS!D31 -> Total Assets | F30: =BS!L31 -> 61991126 | G30: =BS!M31 -> 73493480 | H30: =BS!N31 -> 80286939 | I30: =BS!O31 -> 1.1268951e+08 | J30: =BS!P31 -> 1.4216839e+08 | K30: =BS!Q31 -> 1.7602013e+08 | L30: =BS!R31 -> 2.1185603e+08
D31: =BS!D46 -> Total Non-current Liabilities | F31: =BS!L46 -> 21899764 | G31: =BS!M46 -> 21363092 | H31: =BS!N46 -> 19474701 | I31: =BS!O46 -> 20610285 | J31: =BS!P46 -> 19343705 | K31: =BS!Q46 -> 18676696 | L31: =BS!R46 -> 18410695
D32: =BS!D53 -> Total current Liabilities | F32: =BS!L53 -> 20797634 | G32: =BS!M53 -> 29784496 | H32: =BS!N53 -> 30615411 | I32: =BS!O53 -> 51601410 | J32: =BS!P53 -> 66960050 | K32: =BS!Q53 -> 79857661 | L32: =BS!R53 -> 87519514
D33: =BS!D54 -> Total Liabilities | F33: =BS!L54 -> 42697398 | G33: =BS!M54 -> 51147588 | H33: =BS!N54 -> 50090112 | I33: =BS!O54 -> 72211695 | J33: =BS!P54 -> 86303755 | K33: =BS!Q54 -> 98534357 | L33: =BS!R54 -> 1.0593021e+08
D34: =BS!D38 -> Total Equity | F34: =BS!L38 -> 19293728 | G34: =BS!M38 -> 22345892 | H34: =BS!N38 -> 30196827 | I34: =BS!O38 -> 40477813 | J34: =BS!P38 -> 55864638 | K34: =BS!Q38 -> 77485778 | L34: =BS!R38 -> 1.0592582e+08

Sheet Historical
B2: =COY -> Fidson Healthcare Plc
C3: Historical Financial Statement
D5: ="Balance sheet check: " &BSCheck -> Balance sheet check: OK | I5: Period start | K5: =J6+1 -> 44562 | L5: =K6+1 -> 44927 | M5: =L6+1 -> 45292 | N5: =M6+1 -> 45658 | O5: =N6+1 -> 46023 | P5: =O6+1 -> 46388 | Q5: =P6+1 -> 46753 | R5: =Q6+1 -> 47119
D6: {=livescenario} -> Live Scenario: Base case | I6: Period end | J6: =Guide!E14-1 -> 44561 | K6: =EOMONTH(K5,11) -> 44926 | L6: =EOMONTH(L5,11) -> 45291 | M6: =EOMONTH(M5,11) -> 45657 | N6: =EOMONTH(N5,11) -> 46022 | O6: =EOMONTH(O5,11) -> 46387 | P6: =EOMONTH(P5,11) -> 46752 | Q6: =EOMONTH(Q5,11) -> 47118 | R6: =EOMONTH(R5,11) -> 47483
D8: Description | E8: Units | F8: Inputs | G8: Row totals | K8: Historical | L8: Historical | M8: Historical | N8: Historical | O8: Forecast | P8: Forecast | Q8: Forecast | R8: Forecast
B9: Historical Financial Statement
C10: Income Statement
D11: Revenue | E11: =currency -> (₦'000) | K11: 40634143 | L11: 53050354 | M11: 84189000 | N11: 119061254
D12: Cost of sales | E12: =currency -> (₦'000) | L12: 31979445 | M12: 49084616 | N12: 69835197
D13: Gross Profit | E13: =currency -> (₦'000) | L13: =L11-L12 -> 21070909 | M13: =M11-M12 -> 35104384 | N13: =N11-N12 -> 49226057
D14: Other gains and losses | E14: =currency -> (₦'000) | L14: 497066 | M14: 611871 | N14: 887547
D15: Administrative expenses | E15: =currency -> (₦'000) | L15: 6532831 | M15: 8712125 | N15: 12396055
D16: Impairment of receivables | E16: =currency -> (₦'000) | L16: 227781 | M16: 301440 | N16: 133069
D17: Net exchange loss | E17: =currency -> (₦'000) | L17: 1261246 | M17: 5448891 | N17: 6012067
D18: Selling and distribution expenses | E18: =currency -> (₦'000) | L18: 5549848 | M18: 8119539 | N18: 9623801
D19: Operating profit | E19: =currency -> (₦'000) | L19: =L13+L14-L15-L16-L17-L18 -> 7996269 | M19: =M13+M14-M15-M16-M17-M18 -> 13134260 | N19: =N13+N14-N15-N16-N17-N18 -> 21948612
D20: Finance cost | E20: =currency -> (₦'000) | L20: 2101868 | M20: 5493822 | N20: 7130319
D21: Finance income | E21: =currency -> (₦'000) | L21: 23008 | M21: 60022 | N21: 144315
D22: Profit before taxation | E22: =currency -> (₦'000) | L22: =L19-L20+L21 -> 5917409 | M22: =M19-M20+M21 -> 7700460 | N22: =N19-N20+N21 -> 14962608
D23: Taxation | E23: =currency -> (₦'000) | L23: 2309816 | M23: 3301497 | N23: 5079032
D24: Profit for the year | E24: =currency -> (₦'000) | L24: =L22-L23 -> 3607593 | M24: =M22-M23 -> 4398963 | N24: =N22-N23 -> 9883576
C27: Balance Sheet
C28: Assets
D29: Non-Current Assets
D30: Property, plant and equipment | E30: =currency -> (₦'000) | L30: 22672162 | M30: 25125748 | N30: 30937846
D31: Right of use assets | E31: =currency -> (₦'000) | L31: 315050 | M31: 0 | N31: 0
D32: Intangible Assets | E32: =currency -> (₦'000) | L32: 25577 | M32: 65471 | N32: 238235
D33: Financial assets at FVTOCI | E33: =currency -> (₦'000) | L33: 7730 | M33: 9100 | N33: 12360
D34: Financial assets at amortised cost (non-current) | E34: =currency -> (₦'000) | L34: 16183 | M34: 17915 | N34: 20498
D35: Other Non-Current Financial Asset | E35: =currency -> (₦'000) | L35: 184432 | M35: 198106 | N35: 215936
D36: Total Non-current Assets | L36: =SUM(L30:L35) -> 23221134 | M36: =SUM(M30:M35) -> 25416340 | N36: =SUM(N30:N35) -> 31424875
D37: Current Assets
D38: Inventories | L38: 16356949 | M38: 24182294 | N38: 26547162
D39: Financial assets at amortised cost (current) | L39: 485010 | M39: 242230 | N39: 0
D40: Trade and other receivables | L40: 5887827 | M40: 6208215 | N40: 11068227
D41: Prepayments | L41: 5253563 | M41: 12513033 | N41: 6535857
D42: Cash and cash equivalents | L42: 10786643 | M42: 4931368 | N42: 4710818
D43: Total Current Assets | L43: =SUM(L38:L42) -> 38769992 | M43: =SUM(M38:M42) -> 48077140 | N43: =SUM(N38:N42) -> 48862064
D44: Total Assets | L44: =L43+L36 -> 61991126 | M44: =M43+M36 -> 73493480 | N44: =N43+N36 -> 80286939
D46: Equity
D47: Share capital | L47: 1147498 | M47: 1147498 | N47: 1200000
D48: Share premium | L48: 4829614 | M48: 4829614 | N48: 5009225
D49: Retained earnings | L49: 13313331 | M49: 16364125 | N49: 23979687
D50: Financial Asset reserve | L50: 3285 | M50: 4655 | N50: 7915
D51: Total Equity | L51: =SUM(L47,L49,L48,L50) -> 19293728 | M51: =SUM(M47,M49,M48,M50) -> 22345892 | N51: =SUM(N47,N49,N48,N50) -> 30196827
D53: Liabilities
D54: Non-Current Liabilities
D55: Interest bearing loans and borrowings (non-current) | K55: 5746439 | L55: 6110810 | M55: 7018279 | N55: 3596236
D56: Retirement benefit obligation | L56: 252158 | M56: 251090 | N56: 160139
D57: Government grant | L57: 608963 | M57: 590618 | N57: 207267
D58: Deferred Tax Liability | L58: 2871885 | M58: 3836608 | N58: 4676504
D59: Total Non-current Liabilities | L59: =SUM(L55:L58) -> 9843816 | M59: =SUM(M55:M58) -> 11696595 | N59: =SUM(N55:N58) -> 8640146
D60: Current Liabilities
D61: Trade and other payables | L61: 9076011 | M61: 10370733 | N61: 6630781
D62: Interest bearing loans and borrowings (current) | K62: 5798413 | L62: 11663085 | M62: 8979029 | N62: 10407067
D63: Bank Overdraft | L63: 781784 | M63: 1283797 | N63: 9528
D64: Other financial liabilities | K64: 3000000 | L64: 10000000 | M64: 15646950 | N64: 19645345
D65: Government grant | L65: 392863 | M65: 687468 | N65: 427488
D66: Income tax payable | L66: 839094 | M66: 2349129 | N66: 4250709
D67: Unclaimed dividend | L67: 100745 | M67: 133887 | N67: 79048
D68: Total current Liabilities | L68: =SUM(L61:L67) -> 32853582 | M68: =SUM(M61:M67) -> 39450993 | N68: =SUM(N61:N67) -> 41449966
D69: Total Liabilities | L69: =SUM(L59,L68) -> 42697398 | M69: =SUM(M59,M68) -> 51147588 | N69: =N68+N59 -> 50090112
D71: Total Equity and Liabilities | L71: =SUM(L69,L51) -> 61991126 | M71: =SUM(M69,M51) -> 73493480 | N71: =SUM(N69,N51) -> 80286939
D73: Balance Check | L73: =L44-L71 -> 0 | M73: =M44-M71 -> 0 | N73: =N44-N71 -> 0
B75: Restructuring Notes and Extracts
C76: Income Statement Restructuring
C77: Cost fof Sales
D78: Audited Values | E78: =currency -> (₦'000) | L78: =L12 -> 31979445 | M78: =M12 -> 49084616 | N78: =N12 -> 69835197
D79: Less:
D80: Depreciation of factory PPE | E80: =currency -> (₦'000) | F80: Note 8a | L80: 770176 | M80: 1006144 | N80: 1223130
D81: Personnel Cost | E81: =currency -> (₦'000) | F81: Note 8b | L81: 1608479 | M81: 1989047 | N81: 2315298
D82: Restructured Cost of Sales | E82: =currency -> (₦'000) | L82: =L78-L80-L81 -> 29600790 | M82: =M78-M80-M81 -> 46089425 | N82: =N78-N80-N81 -> 66296769
C84: Administrative expenses
D85: Audited Values | E85: =currency -> (₦'000) | L85: =L15 -> 6532831 | M85: =M15 -> 8712125 | N85: =N15 -> 12396055
D86: Add: Personel cost in COGS | E86: =currency -> (₦'000) | F86: Note 8b | L86: =L81 -> 1608479 | M86: =M81 -> 1989047 | N86: =N81 -> 2315298
D87: Less: Depreciation | E87: =currency -> (₦'000) | F87: Note 8a | L87: 496561 | M87: 661506 | N87: 1015714
D88: Administrative expenses | E88: =currency -> (₦'000) | L88: =L85+L86-L87 -> 7644749 | M88: =M85+M86-M87 -> 10039666 | N88: =N85+N86-N87 -> 13695639
C90: Depreciation & Amortization
D91: Depreciation of PPE | E91: =currency -> (₦'000) | F91: Note 8a | L91: 1127156 | M91: 1496671 | N91: 1948477
D92: Depreciation in Right of use Asset | E92: =currency -> (₦'000) | F92: Note 8a | L92: 57690 | M92: 35384 | N92: 0
D93: Amortization of Intangible Assets | E93: =currency -> (₦'000) | F93: Note 8a | L93: 81891 | M93: 135595 | N93: 290367
D94: Total Depreciation | E94: =currency -> (₦'000) | L94: =L91+L92+L93 -> 1266737 | M94: =M91+M92+M93 -> 1667650 | N94: =N91+N92+N93 -> 2238844
C96: Balance sheet Restructuring
C97: Trade Receivables
D98: Audited Values | E98: =currency -> (₦'000) | L98: =L40 -> 5887827 | M98: =M40 -> 6208215 | N98: =N40 -> 11068227
D99: Less:
D100: Other receivables | E100: =currency -> (₦'000) | F100: Note 22 | L100: =558299-111338 -> 446961 | M100: =1121512-469127 -> 652385 | N100: =841848-589257 -> 252591
D101: Restructured Trade Receivables | E101: =currency -> (₦'000) | L101: =L98-L100 -> 5440866 | M101: =M98-M100 -> 5555830 | N101: =N98-N100 -> 10815636
D102: Restructured Other Receivables | E102: =currency -> (₦'000) | L102: =L98-L101 -> 446961 | M102: =M98-M101 -> 652385 | N102: =N98-N101 -> 252591
C104: Interest bearing loans and borrowings
D105: Audited Values | E105: =currency -> (₦'000) | F105: Note 30 | K105: =K62 -> 5798413 | L105: =L62 -> 11663085 | M105: =M62 -> 8979029 | N105: =N62 -> 10407067
D106: Add: Non-current portion of borrowing | E106: =currency -> (₦'000) | F106: Note 30 | K106: =K55 -> 5746439 | L106: =L55 -> 6110810 | M106: =M55 -> 7018279 | N106: =N55 -> 3596236
D107: Restructured Borrowings | E107: =currency -> (₦'000) | K107: =K105+K106 -> 11544852 | L107: =L105+L106 -> 17773895 | M107: =M105+M106 -> 15997308 | N107: =N105+N106 -> 14003303
C109: Government Grant
D110: Audited Values | E110: =currency -> (₦'000) | L110: =L65 -> 392863 | M110: =M65 -> 687468 | N110: =N65 -> 427488
D111: Add: Non-current portion | E111: =currency -> (₦'000) | L111: =L57 -> 608963 | M111: =M57 -> 590618 | N111: =N57 -> 207267
D112: Restructured Borrowings | E112: =currency -> (₦'000) | L112: =L110+L111 -> 1001826 | M112: =M110+M111 -> 1278086 | N112: =N110+N111 -> 634755
C114: Trade and other Payables
D115: Audited Values | E115: =currency -> (₦'000) | F115: Note 33 | L115: =L61 -> 9076011 | M115: =M61 -> 10370733 | N115: =N61 -> 6630781
D116: Less:
...

Sheet Drivers
B2: =COY -> Fidson Healthcare Plc
C3: Inputs and Assumptions
D5: ="Balance sheet check: " &BSCheck -> Balance sheet check: OK | I5: Period start | K5: =J6+1 -> 44562 | L5: =K6+1 -> 44927 | M5: =L6+1 -> 45292 | N5: =M6+1 -> 45658 | O5: =N6+1 -> 46023 | P5: =O6+1 -> 46388 | Q5: =P6+1 -> 46753 | R5: =Q6+1 -> 47119
D6: {=livescenario} -> Live Scenario: Base case | I6: Period end | J6: =Guide!E14-1 -> 44561 | K6: =EOMONTH(K5,11) -> 44926 | L6: =EOMONTH(L5,11) -> 45291 | M6: =EOMONTH(M5,11) -> 45657 | N6: =EOMONTH(N5,11) -> 46022 | O6: =EOMONTH(O5,11) -> 46387 | P6: =EOMONTH(P5,11) -> 46752 | Q6: =EOMONTH(Q5,11) -> 47118 | R6: =EOMONTH(R5,11) -> 47483
D8: Description | E8: Units | F8: Inputs | G8: Row totals | K8: Historical | L8: Historical | M8: Historical | N8: Historical | O8: Forecast | P8: Forecast | Q8: Forecast | R8: Forecast
B9: P & L Assumptions
C10: Revenue
D11: Revenue from Contract with Customers | E11: % | F11: YoY Growth | L11: =Historical!L11/Historical!K11-1 -> 0.30556104 | M11: =Historical!M11/Historical!L11-1 -> 0.58696396 | N11: =Historical!N11/Historical!M11-1 -> 0.4142139 | O11: =Scenario!O18 -> 0.43557963 | P11: =Scenario!P18 -> 0.37 | Q11: =Scenario!Q18 -> 0.31 | R11: =Scenario!R18 -> 0.25
C13: Cost of Sales
D14: Cost of Sales | E14: % | F14: % of Revenue | L14: ='P or L'!L14/'P or L'!L13 -> 0.55797535 | M14: ='P or L'!M14/'P or L'!M13 -> 0.54745186 | N14: ='P or L'!N14/'P or L'!N13 -> 0.55682908 | O14: =Scenario!O24 -> 0.55408543 | P14: =Scenario!P24 -> 0.55408543 | Q14: =Scenario!Q24 -> 0.55408543 | R14: =Scenario!R24 -> 0.55408543
C16: SGA & Other Losses
D17: Other operating (losses)/gains | E17: % | F17: % of Revenue | L17: ='P or L'!L16/'P or L'!L13 -> 0.0093697018 | M17: ='P or L'!M16/'P or L'!M13 -> 0.007267826 | N17: ='P or L'!N16/'P or L'!N13 -> 0.007454541 | O17: 0.0080306896 | P17: 0.0080306896 | Q17: 0.0080306896 | R17: 0.0080306896
D18: ='P or L'!D17 -> Selling and Distribution costs | E18: % | F18: % of Revenue | L18: ='P or L'!L17/'P or L'!L13 -> 0.10461472 | M18: ='P or L'!M17/'P or L'!M13 -> 0.096444179 | N18: ='P or L'!N17/'P or L'!N13 -> 0.080830671 | O18: =Scenario!O30 -> 0.09396319 | P18: =Scenario!P30 -> 0.09396319 | Q18: =Scenario!Q30 -> 0.09396319 | R18: =Scenario!R30 -> 0.09396319
D19: Administrative expenses | E19: % | F19: % of Revenue | L19: ='P or L'!L18/'P or L'!L13 -> 0.14410364 | M19: ='P or L'!M18/'P or L'!M13 -> 0.11925152 | N19: ='P or L'!N18/'P or L'!N13 -> 0.11503019 | O19: =Scenario!O36 -> 0.12612845 | P19: =Scenario!P36 -> 0.12612845 | Q19: =Scenario!Q36 -> 0.12612845 | R19: =Scenario!R36 -> 0.12612845
C21: Use of Assets
D22: =Historical!D91 -> Depreciation of PPE | E22: % | F22: % of Previous PPE | L22: ='P or L'!L20/BS!K17 -> 0.057609104 | M22: ='P or L'!M20/BS!L17 -> 0.066013599 | N22: ='P or L'!N20/BS!M17 -> 0.077549015 | O22: 0.067057239 | P22: 0.067057239 | Q22: 0.067057239 | R22: 0.067057239
D23: =Historical!D92 -> Depreciation in Right of use Asset | E23: % | F23: % of Previous ROU | L23: ='P or L'!L21/BS!K18 -> 0.15149009 | M23: ='P or L'!M21/BS!L18 -> 0.11231233 | N23: =IFERROR('P or L'!N21/BS!M18,0) -> 0 | O23: 0.087934139 | P23: 0.087934139 | Q23: 0.087934139 | R23: 0.087934139
D24: =Historical!D93 -> Amortization of Intangible Assets | E24: % | F24: % of Previous Intangible Assets | L24: ='P or L'!L22/BS!K19 -> 3.478211 | M24: ='P or L'!M22/BS!L19 -> 5.3014427 | N24: ='P or L'!N22/BS!M19 -> 4.4350476 | O24: 4.4049004 | P24: 4.4049004 | Q24: 4.4049004 | R24: 4.4049004
C26: Other Income Statement Items
D27: ='P or L'!D24 -> Net Foreign Exchange (Loss)/Gain | E27: =currency -> (₦'000) | F27: Flat balance | L27: ='P or L'!L24 -> 1261246 | M27: ='P or L'!M24 -> 5448891 | N27: ='P or L'!N24 -> 6012067 | O27: 5730479 | P27: 5730479 | Q27: 5730479 | R27: 5730479
D28: ='P or L'!D25 -> Impairment of receivables | E28: =currency -> (₦'000) | F28: Flat balance | L28: ='P or L'!L25 -> 227781 | M28: ='P or L'!M25 -> 301440 | N28: ='P or L'!N25 -> 133069 | O28: 217254.5 | P28: 217254.5 | Q28: 217254.5 | R28: 217254.5
D29: ='P or L'!D26 -> Finance income | E29: % | F29: % of previous ending cash | L29: ='P or L'!L26/BS!K29 -> 0.010877788 | M29: ='P or L'!M26/BS!L29 -> 0.0055644745 | N29: ='P or L'!N26/BS!M29 -> 0.029264699 | O29: 0.038119547 | P29: 0.038119547 | Q29: 0.038119547 | R29: 0.038119547
D30: ='P or L'!D27 -> Finance cost | E30: % | F30: % of opening debt (loans + other fin. liabilities + overdraft) | L30: ='P or L'!L27/(BS!K42+BS!K50+BS!K51) -> 0.14450941 | M30: ='P or L'!M27/(BS!L42+BS!L50+BS!L51) -> 0.19238982 | N30: ='P or L'!N27/(BS!M42+BS!M50+BS!M51) -> 0.21654237 | O30: =N30 -> 0.21654237 | P30: =O30 -> 0.21654237 | Q30: =P30 -> 0.21654237 | R30: =Q30 -> 0.21654237
D31: ='P or L'!D29 -> Taxation | E31: % | F31: % of PBT | L31: ='P or L'!L29/'P or L'!L28 -> 0.39034246 | M31: ='P or L'!M29/'P or L'!M28 -> 0.42874023 | N31: ='P or L'!N29/'P or L'!N28 -> 0.33944831 | O31: 0.38409427 | P31: 0.38409427 | Q31: 0.38409427 | R31: 0.38409427
B33: Balance Sheet Assumptions
C34: Property Plant and Equipment
D35: Maintainable CAPEX | E35: factor | F35: Factor of Depreciation | O35: 1.1 | P35: 1.1 | Q35: 1.1 | R35: 1.1
D36: Incremental CAPEX | E36: =currency -> (₦'000) | F36: Management Decision
C38: Right of Use Assets
D39: Maintainable CAPEX | E39: factor | F39: Factor of Depreciation | O39: 1.1 | P39: 1.1 | Q39: 1.1 | R39: 1.1
D40: Incremental CAPEX | E40: =currency -> (₦'000) | F40: Management Decision
C42: Intangible Assets
D43: Maintainable CAPEX | E43: factor | F43: Factor of Amortization | O43: 1.1 | P43: 1.1 | Q43: 1.1 | R43: 1.1
D44: Incremental CAPEX | E44: =currency -> (₦'000) | F44: Management Decision
C46: Other Non-current Assets
D47: =BS!D20 -> Financial assets at FVTOCI | E47: =currency -> (₦'000) | F47: Ending Balance | L47: =BS!L20 -> 7730 | M47: =BS!M20 -> 9100 | N47: =BS!N20 -> 12360 | O47: =N47 -> 12360 | P47: =O47 -> 12360 | Q47: =P47 -> 12360 | R47: =Q47 -> 12360
D48: =BS!D21 -> Financial assets at amortized cost | E48: =currency -> (₦'000) | F48: Ending Balance | L48: =BS!L21 -> 501193 | M48: =BS!M21 -> 260145 | N48: =BS!N21 -> 20498 | O48: =N48 -> 20498 | P48: =O48 -> 20498 | Q48: =P48 -> 20498 | R48: =Q48 -> 20498
D49: =BS!D22 -> Other Non-Current Financial Asset | E49: =currency -> (₦'000) | F49: Ending Balance | L49: =BS!L22 -> 184432 | M49: =BS!M22 -> 198106 | N49: =BS!N22 -> 215936 | O49: =N49 -> 215936 | P49: =O49 -> 215936 | Q49: =P49 -> 215936 | R49: =Q49 -> 215936
C51: Current Assets Inputs
D52: Inventories | E52: % | F52: % of Revenue | L52: =BS!L25/'P or L'!L13 -> 0.30832874 | M52: =BS!M25/'P or L'!M13 -> 0.28723817 | N52: =BS!N25/'P or L'!N13 -> 0.22297062 | O52: 0.27284584 | P52: 0.27284584 | Q52: 0.27284584 | R52: 0.27284584
D53: Trade receivables | E53: % | F53: % of Revenue | L53: =BS!L26/'P or L'!L13 -> 0.10256041 | M53: =BS!M26/'P or L'!M13 -> 0.065992351 | N53: =BS!N26/'P or L'!N13 -> 0.090840938 | O53: 0.086464566 | P53: 0.086464566 | Q53: 0.086464566 | R53: 0.086464566
D54: Other receivables | E54: =currency -> (₦'000) | F54: Ending balance | L54: =BS!L27 -> 446961 | M54: =BS!M27 -> 652385 | N54: =BS!N27 -> 252591 | O54: =N54 -> 252591 | P54: =O54 -> 252591 | Q54: =P54 -> 252591 | R54: =Q54 -> 252591
D55: Prepayment/ Other assets | E55: % | F55: % of COGS | L55: =BS!L28/'P or L'!L14 -> 0.1774805 | M55: =BS!M28/'P or L'!M14 -> 0.27149466 | N55: =BS!N28/'P or L'!N14 -> 0.09858485 | O55: 0.18252 | P55: 0.18252 | Q55: 0.18252 | R55: 0.18252
C57: Equity Assumption
D58: Share capital | E58: =currency -> (₦'000) | F58: Ending Balance | L58: =BS!L34 -> 1147498 | M58: =BS!M34 -> 1147498 | N58: =BS!N34 -> 1200000 | O58: =N58 -> 1200000 | P58: =O58 -> 1200000 | Q58: =P58 -> 1200000 | R58: =Q58 -> 1200000
D59: Share premium | E59: =currency -> (₦'000) | F59: Ending Balance | L59: =BS!L35 -> 4829614 | M59: =BS!M35 -> 4829614 | N59: =BS!N35 -> 5009225 | O59: =N59 -> 5009225 | P59: =O59 -> 5009225 | Q59: =P59 -> 5009225 | R59: =Q59 -> 5009225
D60: Dividend payout ratio | E60: % | F60: % of PAT | L60: =Historical!L127/'P or L'!L30 -> 0.34988648 | M60: =Historical!M127/'P or L'!M30 -> 0.31302787 | N60: =Historical!N127/'P or L'!N30 -> 0.23211922 | O60: 0.29834452 | P60: 0.29834452 | Q60: 0.29834452 | R60: 0.29834452
D61: Financial Asset reserve | E61: =currency -> (₦'000) | F61: Ending Balance | L61: =BS!L37 -> 3285 | M61: =BS!M37 -> 4655 | N61: =BS!N37 -> 7915 | O61: =N61 -> 7915 | P61: =O61 -> 7915 | Q61: =P61 -> 7915 | R61: =Q61 -> 7915
C63: Borrowings
D64: New Borrowings | E64: =currency -> (₦'000) | F64: Flat balance | L64: =Historical!L130 -> 11105017 | M64: =Historical!M130 -> 8300000 | N64: =Historical!N130 -> 6000000 | O64: =Historical!O130 -> 8468339 | P64: =Historical!P130 -> 7589446.3 | Q64: =Historical!Q130 -> 7352595.1 | R64: =Historical!R130 -> 7803460.1
D65: Repayments | E65: =currency -> (₦'000) | F65: Flat balance | L65: =Historical!L129 -> 3602836 | M65: =Historical!M129 -> 9685504 | N65: =Historical!N129 -> 8709925 | O65: =Historical!O129 -> 7332755 | P65: =Historical!P129 -> 8576061.3 | Q65: =Historical!Q129 -> 8206247.1 | R65: =Historical!R129 -> 8038354.5
D66: Loan repayment rate | E66: % | F66: % previous loan balance | L66: =Historical!L129/BS!K42 -> 0.31207295 | M66: =Historical!M129/BS!L42 -> 0.54492862 | N66: =Historical!N129/BS!M42 -> 0.54446192 | O66: 0.46715449 | P66: 0.46715449 | Q66: 0.46715449 | R66: 0.46715449
C68: Other Non-current Liabilities
D69: =BS!D43 -> Retirement benefit obligation | E69: =currency -> (₦'000) | F69: Ending Balance | L69: =BS!L43 -> 252158 | M69: =BS!M43 -> 251090 | N69: =BS!N43 -> 160139 | O69: =N69 -> 160139 | P69: =O69 -> 160139 | Q69: =P69 -> 160139 | R69: =Q69 -> 160139
D70: =BS!D44 -> Government grant | E70: =currency -> (₦'000) | F70: Ending Balance | L70: =BS!L44 -> 1001826 | M70: =BS!M44 -> 1278086 | N70: =BS!N44 -> 634755 | O70: =N70 -> 634755 | P70: =O70 -> 634755 | Q70: =P70 -> 634755 | R70: =Q70 -> 634755
D71: =BS!D45 -> Deferred Tax Liability | E71: =currency -> (₦'000) | F71: Ending Balance | L71: =BS!L45 -> 2871885 | M71: =BS!M45 -> 3836608 | N71: =BS!N45 -> 4676504 | O71: =N71 -> 4676504 | P71: =AVERAGE(M71:O71) -> 4396538.7 | Q71: =AVERAGE(N71:P71) -> 4583182.2 | R71: =AVERAGE(O71:Q71) -> 4552075
C73: Other Financial Liabilities
D74: New Financial Liabilities | E74: =currency -> (₦'000) | F74: Flat balance | L74: =Historical!L133 -> 10000000 | M74: =Historical!M133 -> 15646950 | N74: =Historical!N133 -> 19645345 | O74: 15097432 | P74: 15097432 | Q74: 15097432 | R74: 15097432
D75: Repayments | E75: =currency -> (₦'000) | F75: Flat balance | L75: =Historical!L132 -> 3000000 | M75: =Historical!M132 -> 10000000 | N75: =Historical!N132 -> 15646950 | O75: 9548983.3 | P75: 9548983.3 | Q75: 9548983.3 | R75: 9548983.3
D76: Financial liability repayment rate | E76: % | F76: % previous loan balance | L76: =Historical!L132/BS!K51 -> 1 | M76: =Historical!M132/BS!L51 -> 1 | N76: =Historical!N132/BS!M51 -> 1 | O76: 1 | P76: 1 | Q76: 1 | R76: 1
C78: Other Current Liabilities
D79: Trade payables | E79: % | F79: % of COGS | L79: =BS!L48/'P or L'!L14 -> 0.23812891 | M79: =BS!M48/'P or L'!M14 -> 0.18608698 | N79: =BS!N48/'P or L'!N14 -> 0.067077809 | O79: 0.16376457 | P79: 0.16376457 | Q79: 0.16376457 | R79: 0.16376457
D80: Other Payables | E80: =currency -> (₦'000) | F80: Ending Balance | L80: =BS!L49 -> 2127952 | M80: =BS!M49 -> 1927978 | N80: =BS!N49 -> 2262787 | O80: =N80 -> 2262787 | P80: =O80 -> 2262787 | Q80: =P80 -> 2262787 | R80: =Q80 -> 2262787
D81: =BS!D50 -> Bank Overdraft | E81: =currency -> (₦'000) | F81: Calculated (cash sweep) | L81: =BS!L50 -> 781784 | M81: =BS!M50 -> 1283797 | N81: =BS!N50 -> 9528 | O81: =Calculation!O117 -> 4384741.5 | P81: =Calculation!P117 -> 8940313.6 | Q81: =Calculation!Q117 -> 10380610 | R81: =Calculation!R117 -> 5922617.2
D82: Income tax payable | E82: =currency -> (₦'000) | F82: Ending Balance | L82: =BS!L52 -> 839094 | M82: =BS!M52 -> 2349129 | N82: =BS!N52 -> 4250709 | O82: =N82 -> 4250709 | P82: =O82 -> 4250709 | Q82: =P82 -> 4250709 | R82: =Q82 -> 4250709
D84: Minimum cash balance | E84: =currency -> (₦'000) | F84: Input (revolver draws to keep cash at this level) | O84: 2000000 | P84: 2000000 | Q84: 2000000 | R84: 2000000

Sheet Scenario
B2: =COY -> Fidson Healthcare Plc
C3: Scenario Analysis
D5: ="Balance sheet check: " &BSCheck -> Balance sheet check: OK | I5: Period start | K5: =J6+1 -> 44562 | L5: =K6+1 -> 44927 | M5: =L6+1 -> 45292 | N5: =M6+1 -> 45658 | O5: =N6+1 -> 46023 | P5: =O6+1 -> 46388 | Q5: =P6+1 -> 46753 | R5: =Q6+1 -> 47119
D6: {=livescenario} -> Live Scenario: Base case | I6: Period end | J6: =Guide!E14-1 -> 44561 | K6: =EOMONTH(K5,11) -> 44926 | L6: =EOMONTH(L5,11) -> 45291 | M6: =EOMONTH(M5,11) -> 45657 | N6: =EOMONTH(N5,11) -> 46022 | O6: =EOMONTH(O5,11) -> 46387 | P6: =EOMONTH(P5,11) -> 46752 | Q6: =EOMONTH(Q5,11) -> 47118 | R6: =EOMONTH(R5,11) -> 47483
D8: Description | E8: Units | F8: Inputs | G8: Row totals | K8: Historical | L8: Historical | M8: Historical | N8: Historical | O8: Forecast | P8: Forecast | Q8: Forecast | R8: Forecast
B10: Scenario Analysis
C11: Scenario List
D12: {="Live Scenario: "&INDEX(scenariolist,scenarioswitch)} -> Live Scenario: Base case
D13: Base case | F13: 1
D14: Best case
D15: Worst case
C17: Revenue Growth Rate
D18: Live Scenario: | E18: % | O18: {=INDEX(O19:O21, scenarioswitch)} -> 0.43557963 | P18: {=INDEX(P19:P21, scenarioswitch)} -> 0.37 | Q18: {=INDEX(Q19:Q21, scenarioswitch)} -> 0.31 | R18: {=INDEX(R19:R21, scenarioswitch)} -> 0.25
D19: =D13 -> Base case | E19: % | O19: 0.43557963 | P19: 0.37 | Q19: 0.31 | R19: 0.25
D20: =D14 -> Best case | E20: % | O20: =O19+5% -> 0.48557963 | P20: =P19+5% -> 0.42 | Q20: =Q19+5% -> 0.36 | R20: =R19+5% -> 0.3
D21: =D15 -> Worst case | E21: % | O21: =O19-5% -> 0.38557963 | P21: =P19-5% -> 0.32 | Q21: =Q19-5% -> 0.26 | R21: =R19-5% -> 0.2
C23: COGS as a % of revenue
D24: Live Scenario: | E24: % | O24: {=INDEX(O25:O27, scenarioswitch)} -> 0.55408543 | P24: {=INDEX(P25:P27, scenarioswitch)} -> 0.55408543 | Q24: {=INDEX(Q25:Q27, scenarioswitch)} -> 0.55408543 | R24: {=INDEX(R25:R27, scenarioswitch)} -> 0.55408543
D25: =D19 -> Base case | E25: % | O25: 0.55408543 | P25: 0.55408543 | Q25: 0.55408543 | R25: 0.55408543
D26: =D20 -> Best case | E26: % | O26: =O25-5% -> 0.50408543 | P26: =P25-5% -> 0.50408543 | Q26: =Q25-5% -> 0.50408543 | R26: =R25-5% -> 0.50408543
D27: =D21 -> Worst case | E27: % | O27: =O25+5% -> 0.60408543 | P27: =P25+5% -> 0.60408543 | Q27: =Q25+5% -> 0.60408543 | R27: =R25+5% -> 0.60408543
C29: Selling& Distribution cost as a % of revenue
D30: Live Scenario: | E30: % | O30: {=INDEX(O31:O33, scenarioswitch)} -> 0.09396319 | P30: {=INDEX(P31:P33, scenarioswitch)} -> 0.09396319 | Q30: {=INDEX(Q31:Q33, scenarioswitch)} -> 0.09396319 | R30: {=INDEX(R31:R33, scenarioswitch)} -> 0.09396319
D31: =D25 -> Base case | E31: % | O31: 0.09396319 | P31: 0.09396319 | Q31: 0.09396319 | R31: 0.09396319
D32: =D26 -> Best case | E32: % | O32: =O31-2% -> 0.07396319 | P32: =P31-2% -> 0.07396319 | Q32: =Q31-2% -> 0.07396319 | R32: =R31-2% -> 0.07396319
D33: =D27 -> Worst case | E33: % | O33: =O31+2% -> 0.11396319 | P33: =P31+2% -> 0.11396319 | Q33: =Q31+2% -> 0.11396319 | R33: =R31+2% -> 0.11396319
C35: Admin cost as a % of Revenue
D36: Live Scenario: | E36: % | O36: {=INDEX(O37:O39, scenarioswitch)} -> 0.12612845 | P36: {=INDEX(P37:P39, scenarioswitch)} -> 0.12612845 | Q36: {=INDEX(Q37:Q39, scenarioswitch)} -> 0.12612845 | R36: {=INDEX(R37:R39, scenarioswitch)} -> 0.12612845
D37: =D31 -> Base case | E37: % | O37: 0.12612845 | P37: 0.12612845 | Q37: 0.12612845 | R37: 0.12612845
D38: =D32 -> Best case | E38: % | O38: =O37-5% -> 0.076128449 | P38: =P37-5% -> 0.076128449 | Q38: =Q37-5% -> 0.076128449 | R38: =R37-5% -> 0.076128449
D39: =D33 -> Worst case | E39: % | O39: =O37+5% -> 0.17612845 | P39: =P37+5% -> 0.17612845 | Q39: =Q37+5% -> 0.17612845 | R39: =R37+5% -> 0.17612845

Sheet Calculation
B2: =COY -> Fidson Healthcare Plc
C3: Model Calculations and Schedules
D5: ="Balance sheet check: " &BSCheck -> Balance sheet check: OK | I5: Period start | K5: =J6+1 -> 44562 | L5: =K6+1 -> 44927 | M5: =L6+1 -> 45292 | N5: =M6+1 -> 45658 | O5: =N6+1 -> 46023 | P5: =O6+1 -> 46388 | Q5: =P6+1 -> 46753 | R5: =Q6+1 -> 47119
D6: {=livescenario} -> Live Scenario: Base case | I6: Period end | J6: =Guide!E14-1 -> 44561 | K6: =EOMONTH(K5,11) -> 44926 | L6: =EOMONTH(L5,11) -> 45291 | M6: =EOMONTH(M5,11) -> 45657 | N6: =EOMONTH(N5,11) -> 46022 | O6: =EOMONTH(O5,11) -> 46387 | P6: =EOMONTH(P5,11) -> 46752 | Q6: =EOMONTH(Q5,11) -> 47118 | R6: =EOMONTH(R5,11) -> 47483
D8: Description | E8: Units | F8: Inputs | G8: Row totals | K8: Historical | L8: Historical | M8: Historical | N8: Historical | O8: Forecast | P8: Forecast | Q8: Forecast | R8: Forecast
B10: P & L Calculation & Schedules
C11: Revenue
D12: Revenue from contracts with customers | E12: =currency -> (₦'000) | N12: ='P or L'!N13 -> 119061254 | O12: =N12*(1+Drivers!O11) -> 1.7092191e+08 | P12: =O12*(1+Drivers!P11) -> 2.3416302e+08 | Q12: =P12*(1+Drivers!Q11) -> 3.0675355e+08 | R12: =Q12*(1+Drivers!R11) -> 3.8344194e+08
C14: Cost of Sales
D15: Cost of Sales | E15: =currency -> (₦'000) | N15: ='P or L'!N14 -> 66296769 | O15: =O12*Drivers!O14 -> 94705341 | P15: =P12*Drivers!P14 -> 1.2974632e+08 | Q15: =Q12*Drivers!Q14 -> 1.6996768e+08 | R15: =R12*Drivers!R14 -> 2.124596e+08
C17: SGA & Other Losses
D18: Other operating (losses)/gains | E18: =currency -> (₦'000) | O18: =O12*Drivers!O17 -> 1372620.8 | P18: =P12*Drivers!P17 -> 1880490.5 | Q18: =Q12*Drivers!Q17 -> 2463442.6 | R18: =R12*Drivers!R17 -> 3079303.2
D19: Distribution costs | E19: =currency -> (₦'000) | O19: =O12*Drivers!O18 -> 16060368 | P19: =P12*Drivers!P18 -> 22002704 | Q19: =Q12*Drivers!Q18 -> 28823543 | R19: =R12*Drivers!R18 -> 36029428
D20: Administrative expenses | E20: =currency -> (₦'000) | O20: =O12*Drivers!O19 -> 21558116 | P20: =P12*Drivers!P19 -> 29534618 | Q20: =Q12*Drivers!Q19 -> 38690350 | R20: =R12*Drivers!R19 -> 48362938
C22: Other Income Statement Items
D23: Net Foreign Exchange (Loss)/Gain | E23: =currency -> (₦'000) | F23: Flat balance | O23: =Drivers!O27 -> 5730479 | P23: =Drivers!P27 -> 5730479 | Q23: =Drivers!Q27 -> 5730479 | R23: =Drivers!R27 -> 5730479
D24: (Increase in)/writeback of impairment allowance | E24: =currency -> (₦'000) | F24: Flat balance | O24: =Drivers!O28 -> 217254.5 | P24: =Drivers!P28 -> 217254.5 | Q24: =Drivers!Q28 -> 217254.5 | R24: =Drivers!R28 -> 217254.5
D25: Taxation | E25: =currency -> (₦'000) | F25: % of PBT | O25: ='P or L'!O28*Drivers!O31 -> 9137648.3 | P25: ='P or L'!P28*Drivers!P31 -> 13675672 | Q25: ='P or L'!Q28*Drivers!Q31 -> 19216675 | R25: ='P or L'!R28*Drivers!R31 -> 25277254
D27: Finance cost | O27: =Drivers!O30*(N58+N64+N117) -> 7288421.1 | P27: =Drivers!P30*(O58+O64+O117) -> 9683216.4 | Q27: =Drivers!Q30*(P58+P64+P117) -> 11552747 | R27: =Drivers!R30*(Q58+Q64+Q117) -> 12734446
B29: Balance Sheet Schedule
C30: PPE
D31: Beginning balance | E31: =currency -> (₦'000) | O31: =N34 -> 30937846 | P31: =O34 -> 31145307 | Q31: =P34 -> 31354158 | R31: =Q34 -> 31564411
D32: Add: New CAPEX | E32: =currency -> (₦'000) | O32: =(Drivers!O35*Calculation!O33)+Drivers!O36 -> 2282067.2 | P32: =(Drivers!P35*Calculation!P33)+Drivers!P36 -> 2297370.1 | Q32: =(Drivers!Q35*Calculation!Q33)+Drivers!Q36 -> 2312775.6 | R32: =(Drivers!R35*Calculation!R33)+Drivers!R36 -> 2328284.5
D33: Subtract: Depreciation | E33: =currency -> (₦'000) | O33: =Drivers!O22*Calculation!N34 -> 2074606.5 | P33: =Drivers!P22*Calculation!O34 -> 2088518.3 | Q33: =Drivers!Q22*Calculation!P34 -> 2102523.3 | R33: =Drivers!R22*Calculation!Q34 -> 2116622.2
D34: Ending Balance | E34: =currency -> (₦'000) | N34: =BS!N17 -> 30937846 | O34: =O31+O32-O33 -> 31145307 | P34: =P31+P32-P33 -> 31354158 | Q34: =Q31+Q32-Q33 -> 31564411 | R34: =R31+R32-R33 -> 31776073
C36: Right of Use
D37: Beginning balance | E37: =currency -> (₦'000) | O37: =N40 -> 0 | P37: =O40 -> 0 | Q37: =P40 -> 0 | R37: =Q40 -> 0
D38: Add: New CAPEX | E38: =currency -> (₦'000) | O38: =(Drivers!O39*Calculation!O39)+Drivers!O40 -> 0 | P38: =(Drivers!P39*Calculation!P39)+Drivers!P40 -> 0 | Q38: =(Drivers!Q39*Calculation!Q39)+Drivers!Q40 -> 0 | R38: =(Drivers!R39*Calculation!R39)+Drivers!R40 -> 0
D39: Subtract: Depreciation | E39: =currency -> (₦'000) | O39: =Drivers!O23*Calculation!N40 -> 0 | P39: =Drivers!P23*Calculation!O40 -> 0 | Q39: =Drivers!Q23*Calculation!P40 -> 0 | R39: =Drivers!R23*Calculation!Q40 -> 0
D40: Ending Balance | E40: =currency -> (₦'000) | N40: =BS!N18 -> 0 | O40: =O37+O38-O39 -> 0 | P40: =P37+P38-P39 -> 0 | Q40: =Q37+Q38-Q39 -> 0 | R40: =R37+R38-R39 -> 0
C42: Intangible asset
D43: Beginning balance | E43: =currency -> (₦'000) | O43: =N46 -> 238235 | P43: =O46 -> 343175.15 | Q43: =P46 -> 494340.38 | R43: =Q46 -> 712092.4
D44: Add: New CAPEX | E44: =currency -> (₦'000) | O44: =(Drivers!O43*Calculation!O45)+Drivers!O44 -> 1154341.6 | P44: =(Drivers!P43*Calculation!P45)+Drivers!P44 -> 1662817.6 | Q44: =(Drivers!Q43*Calculation!Q45)+Drivers!Q44 -> 2395272.2 | R44: =(Drivers!R43*Calculation!R45)+Drivers!R44 -> 3450365.7
D45: Subtract: Amortization | E45: =currency -> (₦'000) | O45: =N46*Drivers!O24 -> 1049401.5 | P45: =O46*Drivers!P24 -> 1511652.3 | Q45: =P46*Drivers!Q24 -> 2177520.2 | R45: =Q46*Drivers!R24 -> 3136696.1
D46: Ending Balance | E46: =currency -> (₦'000) | N46: =BS!N19 -> 238235 | O46: =O43+O44-O45 -> 343175.15 | P46: =P43+P44-P45 -> 494340.38 | Q46: =Q43+Q44-Q45 -> 712092.4 | R46: =R43+R44-R45 -> 1025762
C48: Retained earnings
D49: Beginning balance | E49: =currency -> (₦'000) | O49: =N52 -> 23979687 | P49: =O52 -> 34260673 | Q49: =P52 -> 49647498 | R49: =Q52 -> 71268638
D50: Add: Net profit | E50: =currency -> (₦'000) | O50: ='P or L'!O30 -> 14652470 | P50: ='P or L'!P30 -> 21929316 | Q50: ='P or L'!Q30 -> 30814468 | R50: ='P or L'!R30 -> 40532772
D51: Subtract: Dividend paid | E51: =currency -> (₦'000) | O51: =Drivers!O60*'P or L'!O30 -> 4371484.3 | P51: =Drivers!P60*'P or L'!P30 -> 6542491.2 | Q51: =Drivers!Q60*'P or L'!Q30 -> 9193327.7 | R51: =Drivers!R60*'P or L'!R30 -> 12092731
D52: Ending Balance | E52: =currency -> (₦'000) | N52: =BS!N36 -> 23979687 | O52: =O49+O50-O51 -> 34260673 | P52: =P49+P50-P51 -> 49647498 | Q52: =Q49+Q50-Q51 -> 71268638 | R52: =R49+R50-R51 -> 99708680
C54: Interest bearing loans and borrowings
D55: Beginning balance | E55: =currency -> (₦'000) | O55: =N58 -> 14003303 | P55: =O58 -> 15138887 | Q55: =P58 -> 14152272 | R55: =Q58 -> 13298620
D56: Add: New loans | E56: =currency -> (₦'000) | O56: =Historical!O130 -> 8468339 | P56: =Historical!P130 -> 7589446.3 | Q56: =Historical!Q130 -> 7352595.1 | R56: =Historical!R130 -> 7803460.1
D57: Subtract: Repayment | E57: =currency -> (₦'000) | O57: =Historical!O129 -> 7332755 | P57: =Historical!P129 -> 8576061.3 | Q57: =Historical!Q129 -> 8206247.1 | R57: =Historical!R129 -> 8038354.5
D58: Ending Balance | E58: =currency -> (₦'000) | N58: =BS!N42 -> 14003303 | O58: =O55+O56-O57 -> 15138887 | P58: =P55+P56-P57 -> 14152272 | Q58: =Q55+Q56-Q57 -> 13298620 | R58: =R55+R56-R57 -> 13063726
C60: Other Financial Liabilities
D61: Beginning balance | E61: =currency -> (₦'000) | O61: =N64 -> 19645345 | P61: =O64 -> 25193793 | Q61: =P64 -> 30258391 | R61: =Q64 -> 35128871
D62: Add: New loans | E62: =currency -> (₦'000) | O62: =Historical!O133 -> 15097432 | P62: =Historical!P133 -> 16796576 | Q62: =Historical!Q133 -> 17179784 | R62: =Historical!R133 -> 16357930
D63: Subtract: Repayment | E63: =currency -> (₦'000) | O63: =Historical!O132 -> 9548983.3 | P63: =Historical!P132 -> 11731978 | Q63: =Historical!Q132 -> 12309304 | R63: =Historical!R132 -> 11196755
D64: Ending Balance | E64: =currency -> (₦'000) | N64: =BS!N51 -> 19645345 | O64: =O61+O62-O63 -> 25193793 | P64: =P61+P62-P63 -> 30258391 | Q64: =Q61+Q62-Q63 -> 35128871 | R64: =R61+R62-R63 -> 40290047
C66: Share Capital
D67: Beginning balance | E67: =currency -> (₦'000) | O67: =N69 -> 1200000 | P67: =O69 -> 1200000 | Q67: =P69 -> 1200000 | R67: =Q69 -> 1200000
D68: Change Share capital | E68: =currency -> (₦'000) | O68: =Drivers!O58-Drivers!N58 -> 0 | P68: =Drivers!P58-Drivers!O58 -> 0 | Q68: =Drivers!Q58-Drivers!P58 -> 0 | R68: =Drivers!R58-Drivers!Q58 -> 0
D69: Ending Balance | E69: =currency -> (₦'000) | N69: =BS!N34 -> 1200000 | O69: =O67+O68 -> 1200000 | P69: =P67+P68 -> 1200000 | Q69: =Q67+Q68 -> 1200000 | R69: =R67+R68 -> 1200000
C71: Share Premium
D72: Beginning balance | E72: =currency -> (₦'000) | O72: =N74 -> 5009225 | P72: =O74 -> 5009225 | Q72: =P74 -> 5009225 | R72: =Q74 -> 5009225
D73: Change Share premium | E73: =currency -> (₦'000) | O73: =Drivers!O59-Drivers!N59 -> 0 | P73: =Drivers!P59-Drivers!O59 -> 0 | Q73: =Drivers!Q59-Drivers!P59 -> 0 | R73: =Drivers!R59-Drivers!Q59 -> 0
D74: Ending Balance | E74: =currency -> (₦'000) | N74: =BS!N35 -> 5009225 | O74: =O72+O73 -> 5009225 | P74: =P72+P73 -> 5009225 | Q74: =Q72+Q73 -> 5009225 | R74: =R72+R73 -> 5009225
C76: Financial reserve
D77: Beginning balance | E77: =currency -> (₦'000) | O77: =N79 -> 7915 | P77: =O79 -> 7915 | Q77: =P79 -> 7915 | R77: =Q79 -> 7915
D78: Change Financial reserve | E78: =currency -> (₦'000) | O78: =Drivers!O61-Drivers!N61 -> 0 | P78: =Drivers!P61-Drivers!O61 -> 0 | Q78: =Drivers!Q61-Drivers!P61 -> 0 | R78: =Drivers!R61-Drivers!Q61 -> 0
D79: Ending Balance | E79: =currency -> (₦'000) | N79: =BS!N37 -> 7915 | O79: =O77+O78 -> 7915 | P79: =P77+P78 -> 7915 | Q79: =Q77+Q78 -> 7915 | R79: =R77+R78 -> 7915
C81: Financial assets at FVTOCI
D82: Beginning balance | E82: =currency -> (₦'000) | O82: =N84 -> 12360 | P82: =O84 -> 12360 | Q82: =P84 -> 12360 | R82: =Q84 -> 12360
D83: Change Financial assets at FVTOCI | E83: =currency -> (₦'000) | O83: =Drivers!O47-Drivers!N47 -> 0 | P83: =Drivers!P47-Drivers!O47 -> 0 | Q83: =Drivers!Q47-Drivers!P47 -> 0 | R83: =Drivers!R47-Drivers!Q47 -> 0
D84: Ending Balance | E84: =currency -> (₦'000) | N84: =BS!N20 -> 12360 | O84: =O82+O83 -> 12360 | P84: =P82+P83 -> 12360 | Q84: =Q82+Q83 -> 12360 | R84: =R82+R83 -> 12360
C86: Financial assets at amortized cost
D87: Beginning balance | E87: =currency -> (₦'000) | O87: =N89 -> 20498 | P87: =O89 -> 20498 | Q87: =P89 -> 20498 | R87: =Q89 -> 20498
D88: Change Financial assets at amortized cost | E88: =currency -> (₦'000) | O88: =Drivers!O48-Drivers!N48 -> 0 | P88: =Drivers!P48-Drivers!O48 -> 0 | Q88: =Drivers!Q48-Drivers!P48 -> 0 | R88: =Drivers!R48-Drivers!Q48 -> 0
D89: Ending Balance | E89: =currency -> (₦'000) | N89: =BS!N21 -> 20498 | O89: =O87+O88 -> 20498 | P89: =P87+P88 -> 20498 | Q89: =Q87+Q88 -> 20498 | R89: =R87+R88 -> 20498
C91: Other Non-Current Financial Asset
D92: Beginning balance | E92: =currency -> (₦'000) | O92: =N94 -> 215936 | P92: =O94 -> 215936 | Q92: =P94 -> 215936 | R92: =Q94 -> 215936
D93: Change Other Non-Current Financial Asset | E93: =currency -> (₦'000) | O93: =Drivers!O49-Drivers!N49 -> 0 | P93: =Drivers!P49-Drivers!O49 -> 0 | Q93: =Drivers!Q49-Drivers!P49 -> 0 | R93: =Drivers!R49-Drivers!Q49 -> 0
D94: Ending Balance | E94: =currency -> (₦'000) | N94: =BS!N22 -> 215936 | O94: =O92+O93 -> 215936 | P94: =P92+P93 -> 215936 | Q94: =Q92+Q93 -> 215936 | R94: =R92+R93 -> 215936
C96: Retirement benefit obligation
D97: Beginning balance | E97: =currency -> (₦'000) | O97: =N99 -> 160139 | P97: =O99 -> 160139 | Q97: =P99 -> 160139 | R97: =Q99 -> 160139
D98: Change retirement benefit obligation | E98: =currency -> (₦'000) | O98: =Drivers!O69-Drivers!N69 -> 0 | P98: =Drivers!P69-Drivers!O69 -> 0 | Q98: =Drivers!Q69-Drivers!P69 -> 0 | R98: =Drivers!R69-Drivers!Q69 -> 0
D99: Ending Balance | E99: =currency -> (₦'000) | N99: =BS!N43 -> 160139 | O99: =O97+O98 -> 160139 | P99: =P97+P98 -> 160139 | Q99: =Q97+Q98 -> 160139 | R99: =R97+R98 -> 160139
C101: Government grant
D102: Beginning balance | E102: =currency -> (₦'000) | O102: =N104 -> 634755 | P102: =O104 -> 634755 | Q102: =P104 -> 634755 | R102: =Q104 -> 634755
D103: Change Government grant | E103: =currency -> (₦'000) | O103: =Drivers!O70-Drivers!N70 -> 0 | P103: =Drivers!P70-Drivers!O70 -> 0 | Q103: =Drivers!Q70-Drivers!P70 -> 0 | R103: =Drivers!R70-Drivers!Q70 -> 0
D104: Ending Balance | E104: =currency -> (₦'000) | N104: =BS!N44 -> 634755 | O104: =O102+O103 -> 634755 | P104: =P102+P103 -> 634755 | Q104: =Q102+Q103 -> 634755 | R104: =R102+R103 -> 634755
C106: Operating Working Capital Schedule
C107: Asset
D108: =BS!D25 -> Inventories | N108: =BS!N25 -> 26547162 | O108: =Drivers!O52*Calculation!O12 -> 46635333 | P108: =Drivers!P52*Calculation!P12 -> 63890407 | Q108: =Drivers!Q52*Calculation!Q12 -> 83696433 | R108: =Drivers!R52*Calculation!R12 -> 1.0462054e+08
D109: =BS!D26 -> Trade receivables | N109: =BS!N26 -> 10815636 | O109: =Drivers!O53*Calculation!O12 -> 14778689 | P109: =Drivers!P53*Calculation!P12 -> 20246804 | Q109: =Drivers!Q53*Calculation!Q12 -> 26523313 | R109: =Drivers!R53*Calculation!R12 -> 33154141
D110: =BS!D27 -> Other receivables | N110: =BS!N27 -> 252591 | O110: =Drivers!O54 -> 252591 | P110: =Drivers!P54 -> 252591 | Q110: =Drivers!Q54 -> 252591 | R110: =Drivers!R54 -> 252591
D111: =BS!D28 -> Prepayment/ Other assets | N111: =BS!N28 -> 6535857 | O111: =Drivers!O55*Calculation!O15 -> 17285619 | P111: =Drivers!P55*Calculation!P15 -> 23681299 | Q111: =Drivers!Q55*Calculation!Q15 -> 31022501 | R111: =Drivers!R55*Calculation!R15 -> 38778126
D112: Total Current Asset | N112: =SUM(N108:N111) -> 44151246 | O112: =SUM(O108:O111) -> 78952233 | P112: =SUM(P108:P111) -> 1.080711e+08 | Q112: =SUM(Q108:Q111) -> 1.4149484e+08 | R112: =SUM(R108:R111) -> 1.768054e+08
B114: Liabilities
D115: =BS!D48 -> Trade payables | N115: =BS!N48 -> 4447042 | O115: =Drivers!O79*Calculation!O15 -> 15509379 | P115: =Drivers!P79*Calculation!P15 -> 21247850 | Q115: =Drivers!Q79*Calculation!Q15 -> 27834683 | R115: =Drivers!R79*Calculation!R15 -> 34793354
D116: =BS!D49 -> Other Payables | N116: =BS!N49 -> 2262787 | O116: =Drivers!O80 -> 2262787 | P116: =Drivers!P80 -> 2262787 | Q116: =Drivers!Q80 -> 2262787 | R116: =Drivers!R80 -> 2262787
D117: =BS!D50 -> Bank Overdraft | N117: =BS!N50 -> 9528 | O117: =N117+Cashflow!O39 -> 4384741.5 | P117: =O117+Cashflow!P39 -> 8940313.6 | Q117: =P117+Cashflow!Q39 -> 10380610 | R117: =Q117+Cashflow!R39 -> 5922617.2
D118: =BS!D45 -> Deferred Tax Liability | N118: =BS!N45 -> 4676504 | O118: =Drivers!O71 -> 4676504 | P118: =Drivers!P71 -> 4396538.7 | Q118: =Drivers!Q71 -> 4583182.2 | R118: =Drivers!R71 -> 4552075
D119: =BS!D52 -> Income tax payable | N119: =BS!N52 -> 4250709 | O119: =Drivers!O82 -> 4250709 | P119: =Drivers!P82 -> 4250709 | Q119: =Drivers!Q82 -> 4250709 | R119: =Drivers!R82 -> 4250709
D120: Operating Liabilities (excl. overdraft) | N120: =SUM(N115:N116)+N118 -> 11386333 | O120: =SUM(O115:O116)+O118 -> 22448670 | P120: =SUM(P115:P116)+P118 -> 27907175 | Q120: =SUM(Q115:Q116)+Q118 -> 34680652 | R120: =SUM(R115:R116)+R118 -> 41608216
D121: Operating Working Capital | N121: =N112-N120 -> 32764913 | O121: =O112-O120 -> 56503562 | P121: =P112-P120 -> 80163924 | Q121: =Q112-Q120 -> 1.0681419e+08 | R121: =R112-R120 -> 1.3519718e+08
D122: Changes in OWC | O122: =N121-O121 -> -23738649 | P122: =O121-P121 -> -23660362 | Q122: =P121-Q121 -> -26650261 | R122: =Q121-R121 -> -28382998
C125: Finance Income
D126: Cash and cash equivalent | E126: =currency -> (₦'000) | N126: =Cashflow!N44 -> 4710818 | O126: =Cashflow!O44 -> 2000000 | P126: =Cashflow!P44 -> 2000000 | Q126: =Cashflow!Q44 -> 2000000 | R126: =Cashflow!R44 -> 2000000
...

Sheet P or L
B2: =COY -> Fidson Healthcare Plc
C3: Income Statement
D5: ="Balance sheet check: " &BSCheck -> Balance sheet check: OK | I5: Period start | K5: =J6+1 -> 44562 | L5: =K6+1 -> 44927 | M5: =L6+1 -> 45292 | N5: =M6+1 -> 45658 | O5: =N6+1 -> 46023 | P5: =O6+1 -> 46388 | Q5: =P6+1 -> 46753 | R5: =Q6+1 -> 47119
D6: {=livescenario} -> Live Scenario: Base case | I6: Period end | J6: =Guide!E14-1 -> 44561 | K6: =EOMONTH(K5,11) -> 44926 | L6: =EOMONTH(L5,11) -> 45291 | M6: =EOMONTH(M5,11) -> 45657 | N6: =EOMONTH(N5,11) -> 46022 | O6: =EOMONTH(O5,11) -> 46387 | P6: =EOMONTH(P5,11) -> 46752 | Q6: =EOMONTH(Q5,11) -> 47118 | R6: =EOMONTH(R5,11) -> 47483
D8: Description | E8: Units | F8: Inputs | G8: Row totals | K8: Historical | L8: Historical | M8: Historical | N8: Historical | O8: Forecast | P8: Forecast | Q8: Forecast | R8: Forecast
D10: Net Profit from Auditors Financials | L10: 3607593 | M10: 4398963 | N10: 9883576
D11: Recon Check | L11: =IF(L10=L30, "OK", L10-L30) -> OK | M11: =IF(M10=M30, "OK", M10-M30) -> OK | N11: =IF(N10=N30, "OK", N10-N30) -> OK
D13: Revenue from contracts with customers | E13: =currency -> (₦'000) | K13: =Historical!K11 -> 40634143 | L13: =Historical!L11 -> 53050354 | M13: =Historical!M11 -> 84189000 | N13: =Historical!N11 -> 119061254 | O13: =Calculation!O12 -> 1.7092191e+08 | P13: =Calculation!P12 -> 2.3416302e+08 | Q13: =Calculation!Q12 -> 3.0675355e+08 | R13: =Calculation!R12 -> 3.8344194e+08
D14: Cost of Sales | E14: =currency -> (₦'000) | K14: =Historical!K82 -> 0 | L14: =Historical!L82 -> 29600790 | M14: =Historical!M82 -> 46089425 | N14: =Historical!N82 -> 66296769 | O14: =Calculation!O15 -> 94705341 | P14: =Calculation!P15 -> 1.2974632e+08 | Q14: =Calculation!Q15 -> 1.6996768e+08 | R14: =Calculation!R15 -> 2.124596e+08
D15: Gross Profit | E15: =currency -> (₦'000) | L15: =L13-L14 -> 23449564 | M15: =M13-M14 -> 38099575 | N15: =N13-N14 -> 52764485 | O15: =O13-O14 -> 76216570 | P15: =P13-P14 -> 1.044167e+08 | Q15: =Q13-Q14 -> 1.3678588e+08 | R15: =R13-R14 -> 1.7098235e+08
D16: Other operating (losses)/gains | E16: =currency -> (₦'000) | L16: =Historical!L14 -> 497066 | M16: =Historical!M14 -> 611871 | N16: =Historical!N14 -> 887547 | O16: =Calculation!O18 -> 1372620.8 | P16: =Calculation!P18 -> 1880490.5 | Q16: =Calculation!Q18 -> 2463442.6 | R16: =Calculation!R18 -> 3079303.2
D17: Selling and Distribution costs | E17: =currency -> (₦'000) | L17: =Historical!L18 -> 5549848 | M17: =Historical!M18 -> 8119539 | N17: =Historical!N18 -> 9623801 | O17: =Calculation!O19 -> 16060368 | P17: =Calculation!P19 -> 22002704 | Q17: =Calculation!Q19 -> 28823543 | R17: =Calculation!R19 -> 36029428
D18: Administrative expenses | E18: =currency -> (₦'000) | L18: =Historical!L88 -> 7644749 | M18: =Historical!M88 -> 10039666 | N18: =Historical!N88 -> 13695639 | O18: =Calculation!O20 -> 21558116 | P18: =Calculation!P20 -> 29534618 | Q18: =Calculation!Q20 -> 38690350 | R18: =Calculation!R20 -> 48362938
D19: EBITDA | E19: =currency -> (₦'000) | L19: =L15+L16-L17-L18 -> 10752033 | M19: =M15+M16-M17-M18 -> 20552241 | N19: =N15+N16-N17-N18 -> 30332592 | O19: =O15+O16-O17-O18 -> 39970707 | P19: =P15+P16-P17-P18 -> 54759869 | Q19: =Q15+Q16-Q17-Q18 -> 71735428 | R19: =R15+R16-R17-R18 -> 89669285
D20: =Historical!D91 -> Depreciation of PPE | E20: =currency -> (₦'000) | L20: =Historical!L91 -> 1127156 | M20: =Historical!M91 -> 1496671 | N20: =Historical!N91 -> 1948477 | O20: =Calculation!O33 -> 2074606.5 | P20: =Calculation!P33 -> 2088518.3 | Q20: =Calculation!Q33 -> 2102523.3 | R20: =Calculation!R33 -> 2116622.2
D21: =Historical!D92 -> Depreciation in Right of use Asset | E21: =currency -> (₦'000) | L21: =Historical!L92 -> 57690 | M21: =Historical!M92 -> 35384 | N21: =Historical!N92 -> 0 | O21: =Calculation!O39 -> 0 | P21: =Calculation!P39 -> 0 | Q21: =Calculation!Q39 -> 0 | R21: =Calculation!R39 -> 0
D22: =Historical!D93 -> Amortization of Intangible Assets | E22: =currency -> (₦'000) | L22: =Historical!L93 -> 81891 | M22: =Historical!M93 -> 135595 | N22: =Historical!N93 -> 290367 | O22: =Calculation!O45 -> 1049401.5 | P22: =Calculation!P45 -> 1511652.3 | Q22: =Calculation!Q45 -> 2177520.2 | R22: =Calculation!R45 -> 3136696.1
D23: EBIT (Operating Profit) | E23: =currency -> (₦'000) | L23: =L19-L20-L21-L22 -> 9485296 | M23: =M19-M20-M21-M22 -> 18884591 | N23: =N19-N20-N21-N22 -> 28093748 | O23: =O19-O20-O21-O22 -> 36846699 | P23: =P19-P20-P21-P22 -> 51159698 | Q23: =Q19-Q20-Q21-Q22 -> 67455385 | R23: =R19-R20-R21-R22 -> 84415967
D24: Net Foreign Exchange (Loss)/Gain | E24: =currency -> (₦'000) | L24: =Historical!L17 -> 1261246 | M24: =Historical!M17 -> 5448891 | N24: =Historical!N17 -> 6012067 | O24: =Calculation!O23 -> 5730479 | P24: =Calculation!P23 -> 5730479 | Q24: =Calculation!Q23 -> 5730479 | R24: =Calculation!R23 -> 5730479
D25: =Historical!D16 -> Impairment of receivables | E25: =currency -> (₦'000) | L25: =Historical!L16 -> 227781 | M25: =Historical!M16 -> 301440 | N25: =Historical!N16 -> 133069 | O25: =Calculation!O24 -> 217254.5 | P25: =Calculation!P24 -> 217254.5 | Q25: =Calculation!Q24 -> 217254.5 | R25: =Calculation!R24 -> 217254.5
D26: Finance income | E26: =currency -> (₦'000) | L26: =Historical!L21 -> 23008 | M26: =Historical!M21 -> 60022 | N26: =Historical!N21 -> 144315 | O26: =Calculation!O127 -> 179574.25 | P26: =Calculation!P127 -> 76239.093 | Q26: =Calculation!Q127 -> 76239.093 | R26: =Calculation!R127 -> 76239.093
D27: Finance cost | E27: =currency -> (₦'000) | L27: =Historical!L20 -> 2101868 | M27: =Historical!M20 -> 5493822 | N27: =Historical!N20 -> 7130319 | O27: =Calculation!O27 -> 7288421.1 | P27: =Calculation!P27 -> 9683216.4 | Q27: =Calculation!Q27 -> 11552747 | R27: =Calculation!R27 -> 12734446
D28: Profit before taxation | E28: =currency -> (₦'000) | L28: =L23-L24-L25+L26-L27 -> 5917409 | M28: =M23-M24-M25+M26-M27 -> 7700460 | N28: =N23-N24-N25+N26-N27 -> 14962608 | O28: =O23-O24-O25+O26-O27 -> 23790119 | P28: =P23-P24-P25+P26-P27 -> 35604987 | Q28: =Q23-Q24-Q25+Q26-Q27 -> 50031143 | R28: =R23-R24-R25+R26-R27 -> 65810027
D29: Taxation | E29: =currency -> (₦'000) | L29: =Historical!L23 -> 2309816 | M29: =Historical!M23 -> 3301497 | N29: =Historical!N23 -> 5079032 | O29: =Calculation!O25 -> 9137648.3 | P29: =Calculation!P25 -> 13675672 | Q29: =Calculation!Q25 -> 19216675 | R29: =Calculation!R25 -> 25277254
D30: Profit for the year | E30: =currency -> (₦'000) | L30: =L28-L29 -> 3607593 | M30: =M28-M29 -> 4398963 | N30: =N28-N29 -> 9883576 | O30: =O28-O29 -> 14652470 | P30: =P28-P29 -> 21929316 | Q30: =Q28-Q29 -> 30814468 | R30: =R28-R29 -> 40532772

Sheet BS
B2: =COY -> Fidson Healthcare Plc
C3: Balance Sheet
D5: ="Balance sheet check: " &BSCheck -> Balance sheet check: OK | I5: Period start | K5: =J6+1 -> 44562 | L5: =K6+1 -> 44927 | M5: =L6+1 -> 45292 | N5: =M6+1 -> 45658 | O5: =N6+1 -> 46023 | P5: =O6+1 -> 46388 | Q5: =P6+1 -> 46753 | R5: =Q6+1 -> 47119
D6: {=livescenario} -> Live Scenario: Base case | I6: Period end | J6: =Guide!E14-1 -> 44561 | K6: =EOMONTH(K5,11) -> 44926 | L6: =EOMONTH(L5,11) -> 45291 | M6: =EOMONTH(M5,11) -> 45657 | N6: =EOMONTH(N5,11) -> 46022 | O6: =EOMONTH(O5,11) -> 46387 | P6: =EOMONTH(P5,11) -> 46752 | Q6: =EOMONTH(Q5,11) -> 47118 | R6: =EOMONTH(R5,11) -> 47483
D8: Description | E8: Units | F8: Inputs | G8: Row totals | K8: Historical | L8: Historical | M8: Historical | N8: Historical | O8: Forecast | P8: Forecast | Q8: Forecast | R8: Forecast
D10: Total Assets per audit | L10: 61991126 | M10: 73493480 | N10: 80286939
D11: Total Liabilities per audit | G11: BASE - B | L11: 61991126 | M11: 73493480 | N11: 80286939
D12: Recon | G12: BCE - C | L12: =IF(L10+L11=L31+L56, "OK", "Check Again") -> OK | M12: =IF(M10+M11=M31+M56, "OK", "Check Again") -> OK | N12: =IF(N10+N11=N31+N56, "OK", "Check Again") -> OK
G13: OWC - O
B14: Balance Sheet
C15: Asset
D16: Non-Current Assets
D17: =Historical!D30 -> Property, plant and equipment | E17: =currency -> (₦'000) | F17: B | K17: 19565588 | L17: =Historical!L30 -> 22672162 | M17: =Historical!M30 -> 25125748 | N17: =Historical!N30 -> 30937846 | O17: =Calculation!O34 -> 31145307 | P17: =Calculation!P34 -> 31354158 | Q17: =Calculation!Q34 -> 31564411 | R17: =Calculation!R34 -> 31776073
D18: =Historical!D31 -> Right of use assets | E18: =currency -> (₦'000) | F18: B | K18: 380817 | L18: =Historical!L31 -> 315050 | M18: =Historical!M31 -> 0 | N18: =Historical!N31 -> 0 | O18: =Calculation!O40 -> 0 | P18: =Calculation!P40 -> 0 | Q18: =Calculation!Q40 -> 0 | R18: =Calculation!R40 -> 0
D19: =Historical!D32 -> Intangible Assets | E19: =currency -> (₦'000) | F19: B | K19: 23544 | L19: =Historical!L32 -> 25577 | M19: =Historical!M32 -> 65471 | N19: =Historical!N32 -> 238235 | O19: =Calculation!O46 -> 343175.15 | P19: =Calculation!P46 -> 494340.38 | Q19: =Calculation!Q46 -> 712092.4 | R19: =Calculation!R46 -> 1025762
D20: =Historical!D33 -> Financial assets at FVTOCI | E20: =currency -> (₦'000) | F20: C | L20: =Historical!L33 -> 7730 | M20: =Historical!M33 -> 9100 | N20: =Historical!N33 -> 12360 | O20: =Calculation!O84 -> 12360 | P20: =Calculation!P84 -> 12360 | Q20: =Calculation!Q84 -> 12360 | R20: =Calculation!R84 -> 12360
D21: Financial assets at amortized cost | E21: =currency -> (₦'000) | F21: C | L21: =Historical!L124 -> 501193 | M21: =Historical!M124 -> 260145 | N21: =Historical!N124 -> 20498 | O21: =Calculation!O89 -> 20498 | P21: =Calculation!P89 -> 20498 | Q21: =Calculation!Q89 -> 20498 | R21: =Calculation!R89 -> 20498
D22: =Historical!D35 -> Other Non-Current Financial Asset | E22: =currency -> (₦'000) | F22: C | L22: =Historical!L35 -> 184432 | M22: =Historical!M35 -> 198106 | N22: =Historical!N35 -> 215936 | O22: =Calculation!O94 -> 215936 | P22: =Calculation!P94 -> 215936 | Q22: =Calculation!Q94 -> 215936 | R22: =Calculation!R94 -> 215936
D23: Total Non-current Assets | E23: =currency -> (₦'000) | L23: =L17+L18+L19+L20+L21+L22 -> 23706144 | M23: =M17+M18+M19+M20+M21+M22 -> 25658570 | N23: =N17+N18+N19+N20+N21+N22 -> 31424875 | O23: =O17+O18+O19+O20+O21+O22 -> 31737276 | P23: =P17+P18+P19+P20+P21+P22 -> 32097293 | Q23: =Q17+Q18+Q19+Q20+Q21+Q22 -> 32525297 | R23: =R17+R18+R19+R20+R21+R22 -> 33050629
D24: Current Assets
D25: Inventories | E25: =currency -> (₦'000) | F25: O | L25: =Historical!L38 -> 16356949 | M25: =Historical!M38 -> 24182294 | N25: =Historical!N38 -> 26547162 | O25: =Calculation!O108 -> 46635333 | P25: =Calculation!P108 -> 63890407 | Q25: =Calculation!Q108 -> 83696433 | R25: =Calculation!R108 -> 1.0462054e+08
D26: Trade receivables | E26: =currency -> (₦'000) | F26: O | L26: =Historical!L101 -> 5440866 | M26: =Historical!M101 -> 5555830 | N26: =Historical!N101 -> 10815636 | O26: =Calculation!O109 -> 14778689 | P26: =Calculation!P109 -> 20246804 | Q26: =Calculation!Q109 -> 26523313 | R26: =Calculation!R109 -> 33154141
D27: Other receivables | E27: =currency -> (₦'000) | F27: O | L27: =Historical!L102 -> 446961 | M27: =Historical!M102 -> 652385 | N27: =Historical!N102 -> 252591 | O27: =Calculation!O110 -> 252591 | P27: =Calculation!P110 -> 252591 | Q27: =Calculation!Q110 -> 252591 | R27: =Calculation!R110 -> 252591
D28: Prepayment/ Other assets | E28: =currency -> (₦'000) | F28: O | L28: =Historical!L41 -> 5253563 | M28: =Historical!M41 -> 12513033 | N28: =Historical!N41 -> 6535857 | O28: =Calculation!O111 -> 17285619 | P28: =Calculation!P111 -> 23681299 | Q28: =Calculation!Q111 -> 31022501 | R28: =Calculation!R111 -> 38778126
D29: Cash and cash equivalents | E29: =currency -> (₦'000) | K29: 2115136 | L29: =Historical!L42 -> 10786643 | M29: =Historical!M42 -> 4931368 | N29: =Historical!N42 -> 4710818 | O29: =Cashflow!O44 -> 2000000 | P29: =Cashflow!P44 -> 2000000 | Q29: =Cashflow!Q44 -> 2000000 | R29: =Cashflow!R44 -> 2000000
D30: Total Current Assets | E30: =currency -> (₦'000) | L30: =SUM(L25:L29) -> 38284982 | M30: =SUM(M25:M29) -> 47834910 | N30: =SUM(N25:N29) -> 48862064 | O30: =SUM(O25:O29) -> 80952233 | P30: =SUM(P25:P29) -> 1.100711e+08 | Q30: =SUM(Q25:Q29) -> 1.4349484e+08 | R30: =SUM(R25:R29) -> 1.788054e+08
D31: Total Assets | E31: =currency -> (₦'000) | L31: =L23+L30 -> 61991126 | M31: =M23+M30 -> 73493480 | N31: =N23+N30 -> 80286939 | O31: =O23+O30 -> 1.1268951e+08 | P31: =P23+P30 -> 1.4216839e+08 | Q31: =Q23+Q30 -> 1.7602013e+08 | R31: =R23+R30 -> 2.1185603e+08
C33: Equity
D34: Share capital | E34: =currency -> (₦'000) | F34: C | L34: =Historical!L47 -> 1147498 | M34: =Historical!M47 -> 1147498 | N34: =Historical!N47 -> 1200000 | O34: =Calculation!O69 -> 1200000 | P34: =Calculation!P69 -> 1200000 | Q34: =Calculation!Q69 -> 1200000 | R34: =Calculation!R69 -> 1200000
D35: Share premium | E35: =currency -> (₦'000) | F35: C | L35: =Historical!L48 -> 4829614 | M35: =Historical!M48 -> 4829614 | N35: =Historical!N48 -> 5009225 | O35: =Calculation!O74 -> 5009225 | P35: =Calculation!P74 -> 5009225 | Q35: =Calculation!Q74 -> 5009225 | R35: =Calculation!R74 -> 5009225
D36: Retained earnings | E36: =currency -> (₦'000) | F36: B | L36: =Historical!L49 -> 13313331 | M36: =Historical!M49 -> 16364125 | N36: =Historical!N49 -> 23979687 | O36: =Calculation!O52 -> 34260673 | P36: =Calculation!P52 -> 49647498 | Q36: =Calculation!Q52 -> 71268638 | R36: =Calculation!R52 -> 99708680
D37: Financial Asset reserve | E37: =currency -> (₦'000) | F37: C | L37: =Historical!L50 -> 3285 | M37: =Historical!M50 -> 4655 | N37: =Historical!N50 -> 7915 | O37: =Calculation!O79 -> 7915 | P37: =Calculation!P79 -> 7915 | Q37: =Calculation!Q79 -> 7915 | R37: =Calculation!R79 -> 7915
D38: Total Equity | L38: =SUM(L34:L37) -> 19293728 | M38: =SUM(M34:M37) -> 22345892 | N38: =SUM(N34:N37) -> 30196827 | O38: =SUM(O34:O37) -> 40477813 | P38: =SUM(P34:P37) -> 55864638 | Q38: =SUM(Q34:Q37) -> 77485778 | R38: =SUM(R34:R37) -> 1.0592582e+08
C40: Liabilities
D41: Non-Current Liabilities
D42: Interest bearing loans and borrowings | E42: =currency -> (₦'000) | F42: B | K42: =Historical!K107 -> 11544852 | L42: =Historical!L107 -> 17773895 | M42: =Historical!M107 -> 15997308 | N42: =Historical!N107 -> 14003303 | O42: =Calculation!O58 -> 15138887 | P42: =Calculation!P58 -> 14152272 | Q42: =Calculation!Q58 -> 13298620 | R42: =Calculation!R58 -> 13063726
D43: Retirement benefit obligation | E43: =currency -> (₦'000) | F43: C | L43: =Historical!L56 -> 252158 | M43: =Historical!M56 -> 251090 | N43: =Historical!N56 -> 160139 | O43: =Calculation!O99 -> 160139 | P43: =Calculation!P99 -> 160139 | Q43: =Calculation!Q99 -> 160139 | R43: =Calculation!R99 -> 160139
D44: Government grant | E44: =currency -> (₦'000) | F44: C | L44: =Historical!L112 -> 1001826 | M44: =Historical!M112 -> 1278086 | N44: =Historical!N112 -> 634755 | O44: =Calculation!O104 -> 634755 | P44: =Calculation!P104 -> 634755 | Q44: =Calculation!Q104 -> 634755 | R44: =Calculation!R104 -> 634755
D45: Deferred Tax Liability | E45: =currency -> (₦'000) | F45: O | L45: =Historical!L58 -> 2871885 | M45: =Historical!M58 -> 3836608 | N45: =Historical!N58 -> 4676504 | O45: =Calculation!O118 -> 4676504 | P45: =Calculation!P118 -> 4396538.7 | Q45: =Calculation!Q118 -> 4583182.2 | R45: =Calculation!R118 -> 4552075
D46: Total Non-current Liabilities | E46: =currency -> (₦'000) | L46: =SUM(L42:L45) -> 21899764 | M46: =SUM(M42:M45) -> 21363092 | N46: =SUM(N42:N45) -> 19474701 | O46: =SUM(O42:O45) -> 20610285 | P46: =SUM(P42:P45) -> 19343705 | Q46: =SUM(Q42:Q45) -> 18676696 | R46: =SUM(R42:R45) -> 18410695
D47: Current Liabilities
D48: Trade payables | E48: =currency -> (₦'000) | F48: O | L48: =Historical!L118 -> 7048804 | M48: =Historical!M118 -> 8576642 | N48: =Historical!N118 -> 4447042 | O48: =Calculation!O115 -> 15509379 | P48: =Calculation!P115 -> 21247850 | Q48: =Calculation!Q115 -> 27834683 | R48: =Calculation!R115 -> 34793354
D49: Other Payables | E49: =currency -> (₦'000) | F49: O | L49: =Historical!L119 -> 2127952 | M49: =Historical!M119 -> 1927978 | N49: =Historical!N119 -> 2262787 | O49: =Calculation!O116 -> 2262787 | P49: =Calculation!P116 -> 2262787 | Q49: =Calculation!Q116 -> 2262787 | R49: =Calculation!R116 -> 2262787
D50: Bank Overdraft | E50: =currency -> (₦'000) | F50: O | L50: =Historical!L63 -> 781784 | M50: =Historical!M63 -> 1283797 | N50: =Historical!N63 -> 9528 | O50: =Calculation!O117 -> 4384741.5 | P50: =Calculation!P117 -> 8940313.6 | Q50: =Calculation!Q117 -> 10380610 | R50: =Calculation!R117 -> 5922617.2
D51: Other Financial liabilities | E51: =currency -> (₦'000) | F51: B | K51: =Historical!K64 -> 3000000 | L51: =Historical!L64 -> 10000000 | M51: =Historical!M64 -> 15646950 | N51: =Historical!N64 -> 19645345 | O51: =Calculation!O64 -> 25193793 | P51: =Calculation!P64 -> 30258391 | Q51: =Calculation!Q64 -> 35128871 | R51: =Calculation!R64 -> 40290047
D52: Income tax payable | E52: =currency -> (₦'000) | F52: O | L52: =Historical!L66 -> 839094 | M52: =Historical!M66 -> 2349129 | N52: =Historical!N66 -> 4250709 | O52: =Calculation!O119 -> 4250709 | P52: =Calculation!P119 -> 4250709 | Q52: =Calculation!Q119 -> 4250709 | R52: =Calculation!R119 -> 4250709
D53: Total current Liabilities | E53: =currency -> (₦'000) | L53: =SUM(L48:L52) -> 20797634 | M53: =SUM(M48:M52) -> 29784496 | N53: =SUM(N48:N52) -> 30615411 | O53: =SUM(O48:O52) -> 51601410 | P53: =SUM(P48:P52) -> 66960050 | Q53: =SUM(Q48:Q52) -> 79857661 | R53: =SUM(R48:R52) -> 87519514
D54: Total Liabilities | E54: =currency -> (₦'000) | L54: =L53+L46 -> 42697398 | M54: =M53+M46 -> 51147588 | N54: =N53+N46 -> 50090112 | O54: =O53+O46 -> 72211695 | P54: =P53+P46 -> 86303755 | Q54: =Q53+Q46 -> 98534357 | R54: =R53+R46 -> 1.0593021e+08
D56: Total Equity and Liabilities | L56: =L38+L54 -> 61991126 | M56: =M38+M54 -> 73493480 | N56: =N38+N54 -> 80286939 | O56: =O38+O54 -> 1.1268951e+08 | P56: =P38+P54 -> 1.4216839e+08 | Q56: =Q38+Q54 -> 1.7602013e+08 | R56: =R38+R54 -> 2.1185603e+08
D58: Balance Check | E58: =currency -> (₦'000) | F58: =IF(SUM(L58:R58)=0, "OK", "Error") -> OK | L58: =L31-L56 -> 0 | M58: =M31-M56 -> 0 | N58: =N31-N56 -> 0 | O58: =O31-O56 -> 0 | P58: =P31-P56 -> 0 | Q58: =Q31-Q56 -> 0 | R58: =R31-R56 -> 0

Sheet Cashflow
B2: =COY -> Fidson Healthcare Plc
C3: Cashflow Statement
D5: ="Balance sheet check: " &BSCheck -> Balance sheet check: OK | I5: Period start | K5: =J6+1 -> 44562 | L5: =K6+1 -> 44927 | M5: =L6+1 -> 45292 | N5: =M6+1 -> 45658 | O5: =N6+1 -> 46023 | P5: =O6+1 -> 46388 | Q5: =P6+1 -> 46753 | R5: =Q6+1 -> 47119
D6: {=livescenario} -> Live Scenario: Base case | I6: Period end | J6: =Guide!E14-1 -> 44561 | K6: =EOMONTH(K5,11) -> 44926 | L6: =EOMONTH(L5,11) -> 45291 | M6: =EOMONTH(M5,11) -> 45657 | N6: =EOMONTH(N5,11) -> 46022 | O6: =EOMONTH(O5,11) -> 46387 | P6: =EOMONTH(P5,11) -> 46752 | Q6: =EOMONTH(Q5,11) -> 47118 | R6: =EOMONTH(R5,11) -> 47483
D8: Description | E8: Units | F8: Inputs | G8: Row totals | K8: Historical | L8: Historical | M8: Historical | N8: Historical | O8: Forecast | P8: Forecast | Q8: Forecast | R8: Forecast
B9: Cashflow Statement
C10: Cashflow from Operating Activities
D11: EBIT (Operating Profit) | E11: =currency -> (₦'000) | O11: ='P or L'!O23 -> 36846699 | P11: ='P or L'!P23 -> 51159698 | Q11: ='P or L'!Q23 -> 67455385 | R11: ='P or L'!R23 -> 84415967
D12: Add back none cash items: | E12: =currency -> (₦'000)
D13: ='P or L'!D20 -> Depreciation of PPE | E13: =currency -> (₦'000) | O13: ='P or L'!O20 -> 2074606.5 | P13: ='P or L'!P20 -> 2088518.3 | Q13: ='P or L'!Q20 -> 2102523.3 | R13: ='P or L'!R20 -> 2116622.2
D14: ='P or L'!D21 -> Depreciation in Right of use Asset | E14: =currency -> (₦'000) | O14: ='P or L'!O21 -> 0 | P14: ='P or L'!P21 -> 0 | Q14: ='P or L'!Q21 -> 0 | R14: ='P or L'!R21 -> 0
D15: Amortization of Intangible asset | E15: =currency -> (₦'000) | O15: ='P or L'!O22 -> 1049401.5 | P15: ='P or L'!P22 -> 1511652.3 | Q15: ='P or L'!Q22 -> 2177520.2 | R15: ='P or L'!R22 -> 3136696.1
D16: EBITDA | E16: =currency -> (₦'000) | O16: =O11+O13+O14+O15 -> 39970707 | P16: =P11+P13+P14+P15 -> 54759869 | Q16: =Q11+Q13+Q14+Q15 -> 71735428 | R16: =R11+R13+R14+R15 -> 89669285
D17: Changes in Working Capital | E17: =currency -> (₦'000) | O17: =Calculation!O122 -> -23738649 | P17: =Calculation!P122 -> -23660362 | Q17: =Calculation!Q122 -> -26650261 | R17: =Calculation!R122 -> -28382998
D18: Net Foreign Exchange (Loss)/Gain | E18: =currency -> (₦'000) | O18: =-'P or L'!O24 -> -5730479 | P18: =-'P or L'!P24 -> -5730479 | Q18: =-'P or L'!Q24 -> -5730479 | R18: =-'P or L'!R24 -> -5730479
D19: Impairment of receivables | E19: =currency -> (₦'000) | O19: =-'P or L'!O25 -> -217254.5 | P19: =-'P or L'!P25 -> -217254.5 | Q19: =-'P or L'!Q25 -> -217254.5 | R19: =-'P or L'!R25 -> -217254.5
D20: ='P or L'!D26 -> Finance income | E20: =currency -> (₦'000) | O20: ='P or L'!O26 -> 179574.25 | P20: ='P or L'!P26 -> 76239.093 | Q20: ='P or L'!Q26 -> 76239.093 | R20: ='P or L'!R26 -> 76239.093
D21: ='P or L'!D27 -> Finance cost | E21: =currency -> (₦'000) | O21: =-'P or L'!O27 -> -7288421.1 | P21: =-'P or L'!P27 -> -9683216.4 | Q21: =-'P or L'!Q27 -> -11552747 | R21: =-'P or L'!R27 -> -12734446
D22: ='P or L'!D29 -> Taxation | E22: =currency -> (₦'000) | O22: =-'P or L'!O29 -> -9137648.3 | P22: =-'P or L'!P29 -> -13675672 | Q22: =-'P or L'!Q29 -> -19216675 | R22: =-'P or L'!R29 -> -25277254
D23: Total Cashflow from operating Activities | E23: =currency -> (₦'000) | O23: =SUM(O16:O22) -> -5962170.7 | P23: =SUM(P16:P22) -> 1869124 | Q23: =SUM(Q16:Q22) -> 8444250.5 | R23: =SUM(R16:R22) -> 17403093
C25: Cashflow from Investing Activities
D26: CAPEX PPE | E26: =currency -> (₦'000) | O26: =-Calculation!O32 -> -2282067.2 | P26: =-Calculation!P32 -> -2297370.1 | Q26: =-Calculation!Q32 -> -2312775.6 | R26: =-Calculation!R32 -> -2328284.5
D27: CAPEX ROU | E27: =currency -> (₦'000) | O27: =-Calculation!O38 -> 0 | P27: =-Calculation!P38 -> 0 | Q27: =-Calculation!Q38 -> 0 | R27: =-Calculation!R38 -> 0
D28: CAPEX Intangible asset | E28: =currency -> (₦'000) | O28: =-Calculation!O44 -> -1154341.6 | P28: =-Calculation!P44 -> -1662817.6 | Q28: =-Calculation!Q44 -> -2395272.2 | R28: =-Calculation!R44 -> -3450365.7
D29: Total Cashflow Investing activities | O29: =O26+O27+O28 -> -3436408.8 | P29: =P26+P27+P28 -> -3960187.7 | Q29: =Q26+Q27+Q28 -> -4708047.8 | R29: =R26+R27+R28 -> -5778650.2
C31: Cashflow from Financing Activities
D32: Change in Share Capital | O32: =Calculation!O68 -> 0 | P32: =Calculation!P68 -> 0 | Q32: =Calculation!Q68 -> 0 | R32: =Calculation!R68 -> 0
D33: Change in Share Premium | O33: =Calculation!O73 -> 0 | P33: =Calculation!P73 -> 0 | Q33: =Calculation!Q73 -> 0 | R33: =Calculation!R73 -> 0
D34: Dividend paid | O34: =-Calculation!O51 -> -4371484.3 | P34: =-Calculation!P51 -> -6542491.2 | Q34: =-Calculation!Q51 -> -9193327.7 | R34: =-Calculation!R51 -> -12092731
D35: New loans | O35: =Calculation!O56 -> 8468339 | P35: =Calculation!P56 -> 7589446.3 | Q35: =Calculation!Q56 -> 7352595.1 | R35: =Calculation!R56 -> 7803460.1
D36: New other liability | O36: =Calculation!O62 -> 15097432 | P36: =Calculation!P62 -> 16796576 | Q36: =Calculation!Q62 -> 17179784 | R36: =Calculation!R62 -> 16357930
D37: Loan repayment | O37: =-Calculation!O57 -> -7332755 | P37: =-Calculation!P57 -> -8576061.3 | Q37: =-Calculation!Q57 -> -8206247.1 | R37: =-Calculation!R57 -> -8038354.5
D38: Liability repayment | O38: =-Calculation!O63 -> -9548983.3 | P38: =-Calculation!P63 -> -11731978 | Q38: =-Calculation!Q63 -> -12309304 | R38: =-Calculation!R63 -> -11196755
D39: Net draw/(repayment) of bank overdraft | O39: =MAX(-Calculation!N117,Drivers!O84-(O42+O23+O29+SUM(O32:O38))) -> 4375213.5 | P39: =MAX(-Calculation!O117,Drivers!P84-(P42+P23+P29+SUM(P32:P38))) -> 4555572.2 | Q39: =MAX(-Calculation!P117,Drivers!Q84-(Q42+Q23+Q29+SUM(Q32:Q38))) -> 1440296.6 | R39: =MAX(-Calculation!Q117,Drivers!R84-(R42+R23+R29+SUM(R32:R38))) -> -4457993
D40: Total Cashflow from Financing activities | O40: =SUM(O32:O39) -> 6687761.5 | P40: =SUM(P32:P39) -> 2091063.7 | Q40: =SUM(Q32:Q39) -> -3736202.7 | R40: =SUM(R32:R39) -> -11624443
C41: Cash Schedule
D42: Beginning balance | O42: =N44 -> 4710818 | P42: =O44 -> 2000000 | Q42: =P44 -> 2000000 | R42: =Q44 -> 2000000
D43: Net cash generated in period | O43: =O23+O29+O40 -> -2710818 | P43: =P23+P29+P40 -> 0 | Q43: =Q23+Q29+Q40 -> 0 | R43: =R23+R29+R40 -> 0
D44: Ending Balance | N44: =BS!N29 -> 4710818 | O44: =O43+O42 -> 2000000 | P44: =P43+P42 -> 2000000 | Q44: =Q43+Q42 -> 2000000 | R44: =R43+R42 -> 2000000
O46: =O44-BS!O58 -> 2000000 | P46: =P44-BS!P58 -> 2000000 | Q46: =Q44-BS!Q58 -> 2000000 | R46: =R44-BS!R58 -> 2000000

Sheet Analysis
B2: =COY -> Fidson Healthcare Plc
C3: Ratio Analysis
D5: ="Balance sheet check: " &BSCheck -> Balance sheet check: OK | I5: Period start | K5: =J6+1 -> 44562 | L5: =K6+1 -> 44927 | M5: =L6+1 -> 45292 | N5: =M6+1 -> 45658 | O5: =N6+1 -> 46023 | P5: =O6+1 -> 46388 | Q5: =P6+1 -> 46753 | R5: =Q6+1 -> 47119
D6: {=livescenario} -> Live Scenario: Base case | I6: Period end | J6: =Guide!E14-1 -> 44561 | K6: =EOMONTH(K5,11) -> 44926 | L6: =EOMONTH(L5,11) -> 45291 | M6: =EOMONTH(M5,11) -> 45657 | N6: =EOMONTH(N5,11) -> 46022 | O6: =EOMONTH(O5,11) -> 46387 | P6: =EOMONTH(P5,11) -> 46752 | Q6: =EOMONTH(Q5,11) -> 47118 | R6: =EOMONTH(R5,11) -> 47483
D8: Description | E8: Units | F8: Trend | G8: Average | K8: Historical | L8: Historical | M8: Historical | N8: Historical | O8: Forecast | P8: Forecast | Q8: Forecast | R8: Forecast
B10: Ratios and Analysis
C11: Margins and Growth Analysis
D12: Revenue growth | E12: % | G12: =AVERAGE(O12:R12) -> 0.34139491 | L12: =('P or L'!L13/'P or L'!K13)-1 -> 0.30556104 | M12: =('P or L'!M13/'P or L'!L13)-1 -> 0.58696396 | N12: =('P or L'!N13/'P or L'!M13)-1 -> 0.4142139 | O12: =('P or L'!O13/'P or L'!N13)-1 -> 0.43557963 | P12: =('P or L'!P13/'P or L'!O13)-1 -> 0.37 | Q12: =('P or L'!Q13/'P or L'!P13)-1 -> 0.31 | R12: =('P or L'!R13/'P or L'!Q13)-1 -> 0.25
D13: Gross Profit Margin | E13: % | G13: =AVERAGE(O13:R13) -> 0.44591457 | L13: ='P or L'!L15/'P or L'!L13 -> 0.44202465 | M13: ='P or L'!M15/'P or L'!M13 -> 0.45254814 | N13: ='P or L'!N15/'P or L'!N13 -> 0.44317092 | O13: ='P or L'!O15/'P or L'!O13 -> 0.44591457 | P13: ='P or L'!P15/'P or L'!P13 -> 0.44591457 | Q13: ='P or L'!Q15/'P or L'!Q13 -> 0.44591457 | R13: ='P or L'!R15/'P or L'!R13 -> 0.44591457
D14: EBITDA Margin | E14: % | G14: =AVERAGE(O14:R14) -> 0.23385362 | L14: ='P or L'!L19/'P or L'!L13 -> 0.20267599 | M14: ='P or L'!M19/'P or L'!M13 -> 0.24412027 | N14: ='P or L'!N19/'P or L'!N13 -> 0.25476459 | O14: ='P or L'!O19/'P or L'!O13 -> 0.23385362 | P14: ='P or L'!P19/'P or L'!P13 -> 0.23385362 | Q14: ='P or L'!Q19/'P or L'!Q13 -> 0.23385362 | R14: ='P or L'!R19/'P or L'!R13 -> 0.23385362
D15: Net Profit Margin | E15: % | G15: =AVERAGE(O15:R15) -> 0.096384277 | L15: ='P or L'!L30/'P or L'!L13 -> 0.068003184 | M15: ='P or L'!M30/'P or L'!M13 -> 0.052251042 | N15: ='P or L'!N30/'P or L'!N13 -> 0.083012531 | O15: ='P or L'!O30/'P or L'!O13 -> 0.085726109 | P15: ='P or L'!P30/'P or L'!P13 -> 0.093649782 | Q15: ='P or L'!Q30/'P or L'!Q13 -> 0.1004535 | R15: ='P or L'!R30/'P or L'!R13 -> 0.10570772
C17: Returns Analysis
D18: Return on Investment | E18: % | G18: =AVERAGE(O18:R18) -> 0.22480334 | L18: =L19/L20 -> 0.076647019 | M18: =M19/M20 -> 0.08147714 | N18: =N19/N20 -> 0.15480464 | O18: =O19/O20 -> 0.18131891 | P18: =P19/P20 -> 0.2186911 | Q18: =Q19/Q20 -> 0.24472772 | R18: =R19/R20 -> 0.25447562
D19: Net Profit | E19: =currency -> (₦'000) | L19: ='P or L'!L30 -> 3607593 | M19: ='P or L'!M30 -> 4398963 | N19: ='P or L'!N30 -> 9883576 | O19: ='P or L'!O30 -> 14652470 | P19: ='P or L'!P30 -> 21929316 | Q19: ='P or L'!Q30 -> 30814468 | R19: ='P or L'!R30 -> 40532772
D20: Capital Employed | E20: =currency -> (₦'000) | L20: =BS!L38+BS!L42+BS!L51 -> 47067623 | M20: =BS!M38+BS!M42+BS!M51 -> 53990150 | N20: =BS!N38+BS!N42+BS!N51 -> 63845475 | O20: =BS!O38+BS!O42+BS!O51 -> 80810493 | P20: =BS!P38+BS!P42+BS!P51 -> 1.002753e+08 | Q20: =BS!Q38+BS!Q42+BS!Q51 -> 1.2591327e+08 | R20: =BS!R38+BS!R42+BS!R51 -> 1.5927959e+08
D22: Return on Equity | E22: % | G22: =AVERAGE(O22:R22) -> 0.38371573 | L22: =L23/L24 -> 0.18698268 | M22: =M23/M24 -> 0.19685779 | N22: =N23/N24 -> 0.32730512 | O22: =O23/O24 -> 0.3619877 | P22: =P23/P24 -> 0.39254377 | Q22: =Q23/Q24 -> 0.39767902 | R22: =R23/R24 -> 0.38265243
D23: Net Profit | E23: =currency -> (₦'000) | L23: ='P or L'!L30 -> 3607593 | M23: ='P or L'!M30 -> 4398963 | N23: ='P or L'!N30 -> 9883576 | O23: ='P or L'!O30 -> 14652470 | P23: ='P or L'!P30 -> 21929316 | Q23: ='P or L'!Q30 -> 30814468 | R23: ='P or L'!R30 -> 40532772
D24: Total equity | E24: =currency -> (₦'000) | L24: =BS!L38 -> 19293728 | M24: =BS!M38 -> 22345892 | N24: =BS!N38 -> 30196827 | O24: =BS!O38 -> 40477813 | P24: =BS!P38 -> 55864638 | Q24: =BS!Q38 -> 77485778 | R24: =BS!R38 -> 1.0592582e+08
D26: Return on Asset | E26: % | G26: =AVERAGE(O26:R26) -> 0.16266462 | L26: =L27/L28 -> 0.058195313 | M26: =M27/M28 -> 0.059855146 | N26: =N27/N28 -> 0.12310316 | O26: =O27/O28 -> 0.13002515 | P26: =P27/P28 -> 0.15424888 | Q26: =Q27/Q28 -> 0.17506218 | R26: =R27/R28 -> 0.19132225
D27: Net Profit | E27: =currency -> (₦'000) | L27: ='P or L'!L30 -> 3607593 | M27: ='P or L'!M30 -> 4398963 | N27: ='P or L'!N30 -> 9883576 | O27: ='P or L'!O30 -> 14652470 | P27: ='P or L'!P30 -> 21929316 | Q27: ='P or L'!Q30 -> 30814468 | R27: ='P or L'!R30 -> 40532772
D28: Assets | E28: =currency -> (₦'000) | L28: =BS!L31 -> 61991126 | M28: =BS!M31 -> 73493480 | N28: =BS!N31 -> 80286939 | O28: =BS!O31 -> 1.1268951e+08 | P28: =BS!P31 -> 1.4216839e+08 | Q28: =BS!Q31 -> 1.7602013e+08 | R28: =BS!R31 -> 2.1185603e+08
D30: Asset Turnover | E30: Multiple | G30: =AVERAGE(O30:R30) -> 1.6791173 | L30: =L31/L32 -> 0.85577336 | M30: =M31/M32 -> 1.1455302 | N30: =N31/N32 -> 1.4829467 | O30: =O31/O32 -> 1.5167509 | P30: =P31/P32 -> 1.6470821 | Q30: =Q31/Q32 -> 1.7427186 | R30: =R31/R32 -> 1.8099175
D31: ='P or L'!D13 -> Revenue from contracts with customers | E31: =currency -> (₦'000) | L31: ='P or L'!L13 -> 53050354 | M31: ='P or L'!M13 -> 84189000 | N31: ='P or L'!N13 -> 119061254 | O31: ='P or L'!O13 -> 1.7092191e+08 | P31: ='P or L'!P13 -> 2.3416302e+08 | Q31: ='P or L'!Q13 -> 3.0675355e+08 | R31: ='P or L'!R13 -> 3.8344194e+08
D32: =BS!D31 -> Total Assets | E32: =currency -> (₦'000) | L32: =BS!L31 -> 61991126 | M32: =BS!M31 -> 73493480 | N32: =BS!N31 -> 80286939 | O32: =BS!O31 -> 1.1268951e+08 | P32: =BS!P31 -> 1.4216839e+08 | Q32: =BS!Q31 -> 1.7602013e+08 | R32: =BS!R31 -> 2.1185603e+08
C34: Leverage ratios
D35: Interest Coverage Ratio | E35: Multiple | G35: =AVERAGE(O35:R35) -> 5.7016752 | L35: ='P or L'!L23/'P or L'!L27 -> 4.5127934 | M35: ='P or L'!M23/'P or L'!M27 -> 3.4374232 | N35: ='P or L'!N23/'P or L'!N27 -> 3.9400408 | O35: ='P or L'!O23/'P or L'!O27 -> 5.0555118 | P35: ='P or L'!P23/'P or L'!P27 -> 5.2833373 | Q35: ='P or L'!Q23/'P or L'!Q27 -> 5.8389044 | R35: ='P or L'!R23/'P or L'!R27 -> 6.6289471
D36: Current Ratio | E36: Multiple | G36: =AVERAGE(O36:R36) -> 1.7631371 | L36: =BS!L30/BS!L53 -> 1.8408335 | M36: =BS!M30/BS!M53 -> 1.6060339 | N36: =BS!N30/BS!N53 -> 1.5959957 | O36: =BS!O30/BS!O53 -> 1.5687988 | P36: =BS!P30/BS!P53 -> 1.6438324 | Q36: =BS!Q30/BS!Q53 -> 1.7968826 | R36: =BS!R30/BS!R53 -> 2.0430346
D37: Cash Ratio | E37: Multiple | G37: =AVERAGE(O37:R37) -> 0.022512038 | L37: =BS!L29/BS!L54 -> 0.25262998 | M37: =BS!M29/BS!M54 -> 0.096414478 | N37: =BS!N29/BS!N54 -> 0.094046865 | O37: =BS!O29/BS!O54 -> 0.027696345 | P37: =BS!P29/BS!P54 -> 0.023173963 | Q37: =BS!Q29/BS!Q54 -> 0.020297489 | R37: =BS!R29/BS!R54 -> 0.018880356
